{"pkg_name": "digitalfish.counter", "api_calls": "{\"args\":[\"android.os.Parcel$2@c24eee0\"],\"method\":\"invoke\",\"hooked_class\":\"java.util.Locale\",\"hooked_method\":\"readObject\",\"type\":\"reflection\",\"class\":\"java.lang.reflect.Method\",\"timestamp\":1508566163695},{\"args\":[\"android.os.Parcel$2@926bd6\"],\"method\":\"invoke\",\"hooked_class\":\"java.util.Locale\",\"hooked_method\":\"readObject\",\"type\":\"reflection\",\"class\":\"java.lang.reflect.Method\",\"timestamp\":1508566163671},{\"args\":[\"android.os.Parcel$2@18b9c53\"],\"method\":\"invoke\",\"hooked_class\":\"java.util.Locale\",\"hooked_method\":\"readObject\",\"type\":\"reflection\",\"class\":\"java.lang.reflect.Method\",\"timestamp\":1508566163796},{\"args\":[\"/data/user/0/digitalfish.counter/shared_prefs/Clicker_Settings.xml\",\"577\"],\"result\":{\"descriptor\":55},\"method\":\"open\",\"type\":\"file\",\"class\":\"libcore.io.IoBridge\",\"timestamp\":1508566162908},{\"args\":[\"android.os.Parcel$2@1240d0e\"],\"method\":\"invoke\",\"hooked_class\":\"java.util.Locale\",\"hooked_method\":\"readObject\",\"type\":\"reflection\",\"class\":\"java.lang.reflect.Method\",\"timestamp\":1508566163707},{\"args\":[\"android.os.Parcel$2@bb50ca1\"],\"method\":\"invoke\",\"hooked_class\":\"java.util.Locale\",\"hooked_method\":\"readObject\",\"type\":\"reflection\",\"class\":\"java.lang.reflect.Method\",\"timestamp\":1508566163848},{\"args\":[\"android.os.Parcel$2@74d05e\"],\"method\":\"invoke\",\"hooked_class\":\"java.util.Locale\",\"hooked_method\":\"readObject\",\"type\":\"reflection\",\"class\":\"java.lang.reflect.Method\",\"timestamp\":1508566163696},{\"args\":[\"sAwake\",\"false\"],\"result\":{\"mClear\":false,\"mModified\":{\"sUseCount\":1,\"sMainCounterValue\":0,\"sAwake\":false}},\"method\":\"putBoolean\",\"type\":\"globals\",\"class\":\"android.app.SharedPreferencesImpl$EditorImpl\",\"timestamp\":1508566174727},{\"args\":[\"android.os.Parcel$2@43b55e5\"],\"method\":\"invoke\",\"hooked_class\":\"java.util.Locale\",\"hooked_method\":\"readObject\",\"type\":\"reflection\",\"class\":\"java.lang.reflect.Method\",\"timestamp\":1508566163688},{\"args\":[\"android.os.Parcel$2@143ddd8\"],\"method\":\"invoke\",\"hooked_class\":\"java.util.Locale\",\"hooked_method\":\"readObject\",\"type\":\"reflection\",\"class\":\"java.lang.reflect.Method\",\"timestamp\":1508566163826},{\"args\":[\"/data/user/0/digitalfish.counter/shared_prefs/digitalfish.counter_preferences.xml\",\"577\"],\"result\":{\"descriptor\":53},\"method\":\"open\",\"type\":\"file\",\"class\":\"libcore.io.IoBridge\",\"timestamp\":1508566191965},{\"args\":[\"android.os.Parcel$2@55e5e45\"],\"method\":\"invoke\",\"hooked_class\":\"java.util.Locale\",\"hooked_method\":\"readObject\",\"type\":\"reflection\",\"class\":\"java.lang.reflect.Method\",\"timestamp\":1508566163804},{\"args\":[\"android.os.Parcel$2@63a3d67\"],\"method\":\"invoke\",\"hooked_class\":\"java.util.Locale\",\"hooked_method\":\"readObject\",\"type\":\"reflection\",\"class\":\"java.lang.reflect.Method\",\"timestamp\":1508566163652},{\"args\":[\"android.os.Parcel$2@dfa3f1\"],\"method\":\"invoke\",\"hooked_class\":\"java.util.Locale\",\"hooked_method\":\"readObject\",\"type\":\"reflection\",\"class\":\"java.lang.reflect.Method\",\"timestamp\":1508566163669},{\"args\":[\"android.os.Parcel$2@7210b1e\"],\"method\":\"invoke\",\"hooked_class\":\"java.util.Locale\",\"hooked_method\":\"readObject\",\"type\":\"reflection\",\"class\":\"java.lang.reflect.Method\",\"timestamp\":1508566163740},{\"args\":[\"android.os.Parcel$2@6bba34b\"],\"method\":\"invoke\",\"hooked_class\":\"java.util.Locale\",\"hooked_method\":\"readObject\",\"type\":\"reflection\",\"class\":\"java.lang.reflect.Method\",\"timestamp\":1508566163710},{\"args\":[\"android.os.Parcel$2@1b15d40\"],\"method\":\"invoke\",\"hooked_class\":\"java.util.Locale\",\"hooked_method\":\"readObject\",\"type\":\"reflection\",\"class\":\"java.lang.reflect.Method\",\"timestamp\":1508566163717},{\"args\":[\"android.os.Parcel$2@bf3401d\"],\"method\":\"invoke\",\"hooked_class\":\"java.util.Locale\",\"hooked_method\":\"readObject\",\"type\":\"reflection\",\"class\":\"java.lang.reflect.Method\",\"timestamp\":1508566163782},{\"args\":[\"android.os.Parcel$2@e93b2a6\"],\"method\":\"invoke\",\"hooked_class\":\"java.util.Locale\",\"hooked_method\":\"readObject\",\"type\":\"reflection\",\"class\":\"java.lang.reflect.Method\",\"timestamp\":1508566163756},{\"args\":[\"android.os.Parcel$2@48d7531\"],\"method\":\"invoke\",\"hooked_class\":\"java.util.Locale\",\"hooked_method\":\"readObject\",\"type\":\"reflection\",\"class\":\"java.lang.reflect.Method\",\"timestamp\":1508566163828},{\"args\":[\"android.os.Parcel$2@96dcb3e\"],\"method\":\"invoke\",\"hooked_class\":\"java.util.Locale\",\"hooked_method\":\"readObject\",\"type\":\"reflection\",\"class\":\"java.lang.reflect.Method\",\"timestamp\":1508566163819},{\"args\":[\"android.os.Parcel$2@8dd0ec8\"],\"method\":\"invoke\",\"hooked_class\":\"java.util.Locale\",\"hooked_method\":\"readObject\",\"type\":\"reflection\",\"class\":\"java.lang.reflect.Method\",\"timestamp\":1508566163690},{\"args\":[\"sSpeakInterval\",\"25\"],\"result\":{\"mClear\":false,\"mModified\":{\"sSpeakInterval\":25,\"sClickingSoundVolume\":8}},\"method\":\"putInt\",\"type\":\"globals\",\"class\":\"android.app.SharedPreferencesImpl$EditorImpl\",\"timestamp\":1508566191948},{\"args\":[\"android.os.Parcel$2@7a09d9f\"],\"method\":\"invoke\",\"hooked_class\":\"java.util.Locale\",\"hooked_method\":\"readObject\",\"type\":\"reflection\",\"class\":\"java.lang.reflect.Method\",\"timestamp\":1508566163820},{\"args\":[\"android.os.Parcel$2@2c62b5\"],\"method\":\"invoke\",\"hooked_class\":\"java.util.Locale\",\"hooked_method\":\"readObject\",\"type\":\"reflection\",\"class\":\"java.lang.reflect.Method\",\"timestamp\":1508566163823},{\"args\":[\"sUseCount\",\"1\"],\"result\":{\"mClear\":false,\"mModified\":{\"sUseCount\":1,\"sMainCounterValue\":0}},\"method\":\"putInt\",\"type\":\"globals\",\"class\":\"android.app.SharedPreferencesImpl$EditorImpl\",\"timestamp\":1508566183571},{\"args\":[\"android.os.Parcel$2@f7566\"],\"method\":\"invoke\",\"hooked_class\":\"java.util.Locale\",\"hooked_method\":\"readObject\",\"type\":\"reflection\",\"class\":\"java.lang.reflect.Method\",\"timestamp\":1508566163810},{\"args\":[{\"path\":\"/data/app/com.google.android.webview-1/base.apk\"}],\"method\":\"dalvik.system.DexFile\",\"type\":\"dex\",\"class\":\"dalvik.system.DexFile\",\"timestamp\":1508566162306},{\"args\":[\"ro.config.low_ram\",\"false\"],\"result\":\"false\",\"method\":\"get\",\"type\":\"content\",\"class\":\"android.os.SystemProperties\",\"timestamp\":1508566162944},{\"args\":[\"android.os.Parcel$2@bf55ff6\"],\"method\":\"invoke\",\"hooked_class\":\"java.util.Locale\",\"hooked_method\":\"readObject\",\"type\":\"reflection\",\"class\":\"java.lang.reflect.Method\",\"timestamp\":1508566163746},{\"args\":[\"android.os.Parcel$2@5d5a493\"],\"method\":\"invoke\",\"hooked_class\":\"java.util.Locale\",\"hooked_method\":\"readObject\",\"type\":\"reflection\",\"class\":\"java.lang.reflect.Method\",\"timestamp\":1508566163749},{\"args\":[\"android.os.Parcel$2@9fb74bb\"],\"method\":\"invoke\",\"hooked_class\":\"java.util.Locale\",\"hooked_method\":\"readObject\",\"type\":\"reflection\",\"class\":\"java.lang.reflect.Method\",\"timestamp\":1508566163825},{\"args\":[\"sisDoNotShowAgainRateDialog\",\"false\"],\"result\":{\"mClear\":false,\"mModified\":{\"sisDoNotShowAgainRateDialog\":false,\"sMainCounterValue\":0,\"sUseCount\":1,\"sAwake\":false,\"sShowInstructions\":true}},\"method\":\"putBoolean\",\"type\":\"globals\",\"class\":\"android.app.SharedPreferencesImpl$EditorImpl\",\"timestamp\":1508566174732},{\"args\":[\"android.os.Parcel$2@d6ad4fb\"],\"method\":\"invoke\",\"hooked_class\":\"java.util.Locale\",\"hooked_method\":\"readObject\",\"type\":\"reflection\",\"class\":\"java.lang.reflect.Method\",\"timestamp\":1508566163766},{\"args\":[\"android.os.Parcel$2@d48d36\"],\"method\":\"invoke\",\"hooked_class\":\"java.util.Locale\",\"hooked_method\":\"readObject\",\"type\":\"reflection\",\"class\":\"java.lang.reflect.Method\",\"timestamp\":1508566163702},{\"args\":[\"sMainCounterValue\",\"0\"],\"result\":{\"mClear\":false,\"mModified\":{\"sMainCounterValue\":0}},\"method\":\"putInt\",\"type\":\"globals\",\"class\":\"android.app.SharedPreferencesImpl$EditorImpl\",\"timestamp\":1508566162900},{\"args\":[\"android.os.Parcel$2@4af2289\"],\"method\":\"invoke\",\"hooked_class\":\"java.util.Locale\",\"hooked_method\":\"readObject\",\"type\":\"reflection\",\"class\":\"java.lang.reflect.Method\",\"timestamp\":1508566163798},{\"args\":[\"android.os.Parcel$2@ed60416\"],\"method\":\"invoke\",\"hooked_class\":\"java.util.Locale\",\"hooked_method\":\"readObject\",\"type\":\"reflection\",\"class\":\"java.lang.reflect.Method\",\"timestamp\":1508566163829},{\"args\":[\"chbTouchVibrate\",\"true\"],\"result\":{\"mClear\":false,\"mModified\":{\"chbTouchVibrate\":true}},\"method\":\"putBoolean\",\"type\":\"globals\",\"class\":\"android.app.SharedPreferencesImpl$EditorImpl\",\"timestamp\":1508566191941},{\"args\":[\"android.os.Parcel$2@cce1946\"],\"method\":\"invoke\",\"hooked_class\":\"java.util.Locale\",\"hooked_method\":\"readObject\",\"type\":\"reflection\",\"class\":\"java.lang.reflect.Method\",\"timestamp\":1508566163735},{\"args\":[\"android.os.Parcel$2@6e0eec4\"],\"method\":\"invoke\",\"hooked_class\":\"java.util.Locale\",\"hooked_method\":\"readObject\",\"type\":\"reflection\",\"class\":\"java.lang.reflect.Method\",\"timestamp\":1508566163770},{\"args\":[\"android.os.Parcel$2@1192ebc\"],\"method\":\"invoke\",\"hooked_class\":\"java.util.Locale\",\"hooked_method\":\"readObject\",\"type\":\"reflection\",\"class\":\"java.lang.reflect.Method\",\"timestamp\":1508566163802},{\"args\":[\"android.os.Parcel$2@7b9946a\"],\"method\":\"invoke\",\"hooked_class\":\"java.util.Locale\",\"hooked_method\":\"readObject\",\"type\":\"reflection\",\"class\":\"java.lang.reflect.Method\",\"timestamp\":1508566163699},{\"args\":[],\"result\":\"\",\"method\":\"getNetworkCountryIso\",\"type\":\"fingerprint\",\"class\":\"android.telephony.TelephonyManager\",\"timestamp\":1508566162700},{\"args\":[\"android.os.Parcel$2@babf6ef\"],\"method\":\"invoke\",\"hooked_class\":\"java.util.Locale\",\"hooked_method\":\"readObject\",\"type\":\"reflection\",\"class\":\"java.lang.reflect.Method\",\"timestamp\":1508566163751},{\"args\":[\"/data/user/0/digitalfish.counter/shared_prefs/Clicker_Settings.xml\",\"577\"],\"result\":{\"descriptor\":55},\"method\":\"open\",\"type\":\"file\",\"class\":\"libcore.io.IoBridge\",\"timestamp\":1508566191951},{\"args\":[\"android.os.Parcel$2@ba5c033\"],\"method\":\"invoke\",\"hooked_class\":\"java.util.Locale\",\"hooked_method\":\"readObject\",\"type\":\"reflection\",\"class\":\"java.lang.reflect.Method\",\"timestamp\":1508566163835},{\"args\":[{\"mDebugUnregister\":false},{\"mHasPartialTypes\":false,\"mPriority\":0,\"mActions\":[\"android.intent.action.USER_PRESENT\",\"android.intent.action.SCREEN_OFF\"],\"mVerifyState\":0}],\"method\":\"registerReceiver\",\"type\":\"binder\",\"class\":\"android.app.ContextImpl\",\"timestamp\":1508566162713},{\"args\":[\"android.os.Parcel$2@b264ba2\"],\"method\":\"invoke\",\"hooked_class\":\"java.util.Locale\",\"hooked_method\":\"readObject\",\"type\":\"reflection\",\"class\":\"java.lang.reflect.Method\",\"timestamp\":1508566163834},{\"args\":[\"android.os.Parcel$2@836c0dc\"],\"method\":\"invoke\",\"hooked_class\":\"java.util.Locale\",\"hooked_method\":\"readObject\",\"type\":\"reflection\",\"class\":\"java.lang.reflect.Method\",\"timestamp\":1508566163687},{\"args\":[\"sUseCount\",\"1\"],\"result\":{\"mClear\":false,\"mModified\":{\"sUseCount\":1,\"sMainCounterValue\":0}},\"method\":\"putInt\",\"type\":\"globals\",\"class\":\"android.app.SharedPreferencesImpl$EditorImpl\",\"timestamp\":1508566162902},{\"args\":[\"android.os.Parcel$2@2832e41\"],\"method\":\"invoke\",\"hooked_class\":\"java.util.Locale\",\"hooked_method\":\"readObject\",\"type\":\"reflection\",\"class\":\"java.lang.reflect.Method\",\"timestamp\":1508566163712},{\"args\":[\"android.os.Parcel$2@c83168a\"],\"method\":\"invoke\",\"hooked_class\":\"java.util.Locale\",\"hooked_method\":\"readObject\",\"type\":\"reflection\",\"class\":\"java.lang.reflect.Method\",\"timestamp\":1508566163766},{\"args\":[\"android.os.Parcel$2@f8582\"],\"method\":\"invoke\",\"hooked_class\":\"java.util.Locale\",\"hooked_method\":\"readObject\",\"type\":\"reflection\",\"class\":\"java.lang.reflect.Method\",\"timestamp\":1508566163748},{\"args\":[\"ro.config.low_ram\",\"false\"],\"result\":\"false\",\"method\":\"get\",\"type\":\"content\",\"class\":\"android.os.SystemProperties\",\"timestamp\":1508566191894},{\"args\":[\"android.os.Parcel$2@bfb7686\"],\"method\":\"invoke\",\"hooked_class\":\"java.util.Locale\",\"hooked_method\":\"readObject\",\"type\":\"reflection\",\"class\":\"java.lang.reflect.Method\",\"timestamp\":1508566163691},{\"args\":[\"/data/user/0/digitalfish.counter/shared_prefs/digitalfish.counter_preferences.xml\",\"577\"],\"result\":{\"descriptor\":53},\"method\":\"open\",\"type\":\"file\",\"class\":\"libcore.io.IoBridge\",\"timestamp\":1508566191946},{\"args\":[\"ro.config.low_ram\",\"false\"],\"result\":\"false\",\"method\":\"get\",\"type\":\"content\",\"class\":\"android.os.SystemProperties\",\"timestamp\":1508566191893},{\"args\":[\"/data/user/0/digitalfish.counter/shared_prefs/WebViewChromiumPrefs.xml\",\"577\"],\"result\":{\"descriptor\":17},\"method\":\"open\",\"type\":\"file\",\"class\":\"libcore.io.IoBridge\",\"timestamp\":1508566162387},{\"args\":[\"android.os.Parcel$2@a2bb714\"],\"method\":\"invoke\",\"hooked_class\":\"java.util.Locale\",\"hooked_method\":\"readObject\",\"type\":\"reflection\",\"class\":\"java.lang.reflect.Method\",\"timestamp\":1508566163653},{\"args\":[\"android.os.Parcel$2@acaa709\"],\"method\":\"invoke\",\"hooked_class\":\"java.util.Locale\",\"hooked_method\":\"readObject\",\"type\":\"reflection\",\"class\":\"java.lang.reflect.Method\",\"timestamp\":1508566163706},{\"args\":[\"android.os.Parcel$2@7234903\"],\"method\":\"invoke\",\"hooked_class\":\"java.util.Locale\",\"hooked_method\":\"readObject\",\"type\":\"reflection\",\"class\":\"java.lang.reflect.Method\",\"timestamp\":1508566163656},{\"args\":[\"chbDecrementButton\",\"false\"],\"result\":{\"mClear\":false,\"mModified\":{\"chbDecrementButton\":false}},\"method\":\"putBoolean\",\"type\":\"globals\",\"class\":\"android.app.SharedPreferencesImpl$EditorImpl\",\"timestamp\":1508566191938},{\"args\":[\"sisDoNotShowAgainRateDialog\",\"false\"],\"result\":{\"mClear\":false,\"mModified\":{\"sisDoNotShowAgainRateDialog\":false,\"sMainCounterValue\":0,\"sUseCount\":1,\"sAwake\":false,\"sShowInstructions\":true}},\"method\":\"putBoolean\",\"type\":\"globals\",\"class\":\"android.app.SharedPreferencesImpl$EditorImpl\",\"timestamp\":1508566169870},{\"args\":[\"android.os.Parcel$2@eedaac5\"],\"method\":\"invoke\",\"hooked_class\":\"java.util.Locale\",\"hooked_method\":\"readObject\",\"type\":\"reflection\",\"class\":\"java.lang.reflect.Method\",\"timestamp\":1508566163709},{\"args\":[\"android.os.Parcel$2@c6e53bf\"],\"method\":\"invoke\",\"hooked_class\":\"java.util.Locale\",\"hooked_method\":\"readObject\",\"type\":\"reflection\",\"class\":\"java.lang.reflect.Method\",\"timestamp\":1508566163786},{\"args\":[\"android.os.Parcel$2@8d52575\"],\"method\":\"invoke\",\"hooked_class\":\"java.util.Locale\",\"hooked_method\":\"readObject\",\"type\":\"reflection\",\"class\":\"java.lang.reflect.Method\",\"timestamp\":1508566163661},{\"args\":[\"android.os.Parcel$2@1e605de\"],\"method\":\"invoke\",\"hooked_class\":\"java.util.Locale\",\"hooked_method\":\"readObject\",\"type\":\"reflection\",\"class\":\"java.lang.reflect.Method\",\"timestamp\":1508566163785},{\"args\":[\"android.os.Parcel$2@d380a8c\"],\"method\":\"invoke\",\"hooked_class\":\"java.util.Locale\",\"hooked_method\":\"readObject\",\"type\":\"reflection\",\"class\":\"java.lang.reflect.Method\",\"timestamp\":1508566163787},{\"args\":[\"android.os.Parcel$2@fef0d6c\"],\"method\":\"invoke\",\"hooked_class\":\"java.util.Locale\",\"hooked_method\":\"readObject\",\"type\":\"reflection\",\"class\":\"java.lang.reflect.Method\",\"timestamp\":1508566163720},{\"args\":[\"android.os.Parcel$2@ce0cd0\"],\"method\":\"invoke\",\"hooked_class\":\"java.util.Locale\",\"hooked_method\":\"readObject\",\"type\":\"reflection\",\"class\":\"java.lang.reflect.Method\",\"timestamp\":1508566163750},{\"args\":[\"android.os.Parcel$2@b547ba0\"],\"method\":\"invoke\",\"hooked_class\":\"java.util.Locale\",\"hooked_method\":\"readObject\",\"type\":\"reflection\",\"class\":\"java.lang.reflect.Method\",\"timestamp\":1508566163739},{\"args\":[\"android.os.Parcel$2@a79128\"],\"method\":\"invoke\",\"hooked_class\":\"java.util.Locale\",\"hooked_method\":\"readObject\",\"type\":\"reflection\",\"class\":\"java.lang.reflect.Method\",\"timestamp\":1508566163711},{\"args\":[\"ro.config.low_ram\",\"false\"],\"result\":\"false\",\"method\":\"get\",\"type\":\"content\",\"class\":\"android.os.SystemProperties\",\"timestamp\":1508566191892},{\"args\":[\"android.os.Parcel$2@f2cfbb7\"],\"method\":\"invoke\",\"hooked_class\":\"java.util.Locale\",\"hooked_method\":\"readObject\",\"type\":\"reflection\",\"class\":\"java.lang.reflect.Method\",\"timestamp\":1508566163792},{\"args\":[\"android.os.Parcel$2@5973080\"],\"method\":\"invoke\",\"hooked_class\":\"java.util.Locale\",\"hooked_method\":\"readObject\",\"type\":\"reflection\",\"class\":\"java.lang.reflect.Method\",\"timestamp\":1508566163657},{\"args\":[\"org.chromium.android_webview.ResourcesContextWrapperFactory$WebViewContextWrapper@8e72b64\",{}],\"method\":\"invoke\",\"hooked_class\":\"\",\"hooked_method\":\"getUserOptInPreference\",\"type\":\"reflection\",\"class\":\"java.lang.reflect.Method\",\"timestamp\":1508566162487},{\"args\":[\"android.os.Parcel$2@1abefa5\"],\"method\":\"invoke\",\"hooked_class\":\"java.util.Locale\",\"hooked_method\":\"readObject\",\"type\":\"reflection\",\"class\":\"java.lang.reflect.Method\",\"timestamp\":1508566163731},{\"args\":[\"android.os.Parcel$2@ea16f62\"],\"method\":\"invoke\",\"hooked_class\":\"java.util.Locale\",\"hooked_method\":\"readObject\",\"type\":\"reflection\",\"class\":\"java.lang.reflect.Method\",\"timestamp\":1508566163676},{\"args\":[\"android.os.Parcel$2@85da70d\"],\"method\":\"invoke\",\"hooked_class\":\"java.util.Locale\",\"hooked_method\":\"readObject\",\"type\":\"reflection\",\"class\":\"java.lang.reflect.Method\",\"timestamp\":1508566163704},{\"args\":[\"android.os.Parcel$2@d80d883\"],\"method\":\"invoke\",\"hooked_class\":\"java.util.Locale\",\"hooked_method\":\"readObject\",\"type\":\"reflection\",\"class\":\"java.lang.reflect.Method\",\"timestamp\":1508566163760},{\"args\":[\"android.os.Parcel$2@a0da28e\"],\"method\":\"invoke\",\"hooked_class\":\"java.util.Locale\",\"hooked_method\":\"readObject\",\"type\":\"reflection\",\"class\":\"java.lang.reflect.Method\",\"timestamp\":1508566163800},{\"args\":[\"sAwake\",\"false\"],\"result\":{\"mClear\":false,\"mModified\":{\"sUseCount\":1,\"sMainCounterValue\":0,\"sAwake\":false}},\"method\":\"putBoolean\",\"type\":\"globals\",\"class\":\"android.app.SharedPreferencesImpl$EditorImpl\",\"timestamp\":1508566169867},{\"args\":[\"android.os.Parcel$2@2617c06\"],\"method\":\"invoke\",\"hooked_class\":\"java.util.Locale\",\"hooked_method\":\"readObject\",\"type\":\"reflection\",\"class\":\"java.lang.reflect.Method\",\"timestamp\":1508566163780},{\"args\":[\"android.os.Parcel$2@75a8f98\"],\"method\":\"invoke\",\"hooked_class\":\"java.util.Locale\",\"hooked_method\":\"readObject\",\"type\":\"reflection\",\"class\":\"java.lang.reflect.Method\",\"timestamp\":1508566163664},{\"args\":[\"android.os.Parcel$2@845599a\"],\"method\":\"invoke\",\"hooked_class\":\"java.util.Locale\",\"hooked_method\":\"readObject\",\"type\":\"reflection\",\"class\":\"java.lang.reflect.Method\",\"timestamp\":1508566163805},{\"args\":[\"android.os.Parcel$2@3d21eb8\"],\"method\":\"invoke\",\"hooked_class\":\"java.util.Locale\",\"hooked_method\":\"readObject\",\"type\":\"reflection\",\"class\":\"java.lang.reflect.Method\",\"timestamp\":1508566163744},{\"args\":[\"/data/app/com.google.android.webview-1/base.apk\",\"0\"],\"result\":{\"descriptor\":16},\"method\":\"open\",\"type\":\"file\",\"class\":\"libcore.io.IoBridge\",\"timestamp\":1508566162343},{\"args\":[\"android.os.Parcel$2@a5329b1\"],\"method\":\"invoke\",\"hooked_class\":\"java.util.Locale\",\"hooked_method\":\"readObject\",\"type\":\"reflection\",\"class\":\"java.lang.reflect.Method\",\"timestamp\":1508566163723},{\"args\":[\"android.os.Parcel$2@adf2a6e\"],\"method\":\"invoke\",\"hooked_class\":\"java.util.Locale\",\"hooked_method\":\"readObject\",\"type\":\"reflection\",\"class\":\"java.lang.reflect.Method\",\"timestamp\":1508566163729},{\"args\":[\"android.os.Parcel$2@6796e5d\"],\"method\":\"invoke\",\"hooked_class\":\"java.util.Locale\",\"hooked_method\":\"readObject\",\"type\":\"reflection\",\"class\":\"java.lang.reflect.Method\",\"timestamp\":1508566163737},{\"args\":[\"android.os.Parcel$2@107725f\"],\"method\":\"invoke\",\"hooked_class\":\"java.util.Locale\",\"hooked_method\":\"readObject\",\"type\":\"reflection\",\"class\":\"java.lang.reflect.Method\",\"timestamp\":1508566163659},{\"args\":[\"android.os.Parcel$2@a33d5be\"],\"method\":\"invoke\",\"hooked_class\":\"java.util.Locale\",\"hooked_method\":\"readObject\",\"type\":\"reflection\",\"class\":\"java.lang.reflect.Method\",\"timestamp\":1508566163718},{\"args\":[\"android.os.Parcel$2@660555a\"],\"method\":\"invoke\",\"hooked_class\":\"java.util.Locale\",\"hooked_method\":\"readObject\",\"type\":\"reflection\",\"class\":\"java.lang.reflect.Method\",\"timestamp\":1508566163646},{\"args\":[\"android.os.Parcel$2@1c9acfa\"],\"method\":\"invoke\",\"hooked_class\":\"java.util.Locale\",\"hooked_method\":\"readObject\",\"type\":\"reflection\",\"class\":\"java.lang.reflect.Method\",\"timestamp\":1508566163844},{\"args\":[\"txtSpeakInterval\",\"25\"],\"result\":{\"mClear\":false,\"mModified\":{\"txtSpeakInterval\":\"25\"}},\"method\":\"putString\",\"type\":\"globals\",\"class\":\"android.app.SharedPreferencesImpl$EditorImpl\",\"timestamp\":1508566191943},{\"args\":[{\"mDebugUnregister\":false},{\"mHasPartialTypes\":false,\"mPriority\":0,\"mActions\":[\"android.intent.action.PROXY_CHANGE\"],\"mVerifyState\":0}],\"method\":\"registerReceiver\",\"type\":\"binder\",\"class\":\"android.app.ContextImpl\",\"timestamp\":1508566162561},{\"args\":[\"android.os.Parcel$2@184f74\"],\"method\":\"invoke\",\"hooked_class\":\"java.util.Locale\",\"hooked_method\":\"readObject\",\"type\":\"reflection\",\"class\":\"java.lang.reflect.Method\",\"timestamp\":1508566163692},{\"args\":[\"android.os.Parcel$2@f3e40a7\"],\"method\":\"invoke\",\"hooked_class\":\"java.util.Locale\",\"hooked_method\":\"readObject\",\"type\":\"reflection\",\"class\":\"java.lang.reflect.Method\",\"timestamp\":1508566163811},{\"args\":[\"android.os.Parcel$2@1844043\"],\"method\":\"invoke\",\"hooked_class\":\"java.util.Locale\",\"hooked_method\":\"readObject\",\"type\":\"reflection\",\"class\":\"java.lang.reflect.Method\",\"timestamp\":1508566163816},{\"args\":[\"/data/data/com.devadvance.rootcloak2/shared_prefs/CustomizeCommands.xml\",\"0\"],\"result\":{\"descriptor\":15},\"method\":\"open\",\"type\":\"file\",\"class\":\"libcore.io.IoBridge\",\"timestamp\":1508566162317},{\"args\":[\"android.os.Parcel$2@f43894\"],\"method\":\"invoke\",\"hooked_class\":\"java.util.Locale\",\"hooked_method\":\"readObject\",\"type\":\"reflection\",\"class\":\"java.lang.reflect.Method\",\"timestamp\":1508566163758},{\"args\":[\"webviewchromium\"],\"result\":\"/data/app/com.google.android.webview-1/lib/arm/libwebviewchromium.so\",\"method\":\"findLibrary\",\"type\":\"dex\",\"class\":\"dalvik.system.BaseDexClassLoader\",\"timestamp\":1508566162341},{\"args\":[\"android.os.Parcel$2@b8cd463\"],\"method\":\"invoke\",\"hooked_class\":\"java.util.Locale\",\"hooked_method\":\"readObject\",\"type\":\"reflection\",\"class\":\"java.lang.reflect.Method\",\"timestamp\":1508566163783},{\"args\":[\"ro.config.low_ram\",\"false\"],\"result\":\"false\",\"method\":\"get\",\"type\":\"content\",\"class\":\"android.os.SystemProperties\",\"timestamp\":1508566191987},{\"args\":[\"android.os.Parcel$2@e1d16e1\"],\"method\":\"invoke\",\"hooked_class\":\"java.util.Locale\",\"hooked_method\":\"readObject\",\"type\":\"reflection\",\"class\":\"java.lang.reflect.Method\",\"timestamp\":1508566163779},{\"args\":[\"sMainCounterValue\",\"0\"],\"result\":{\"mClear\":false,\"mModified\":{\"sMainCounterValue\":0}},\"method\":\"putInt\",\"type\":\"globals\",\"class\":\"android.app.SharedPreferencesImpl$EditorImpl\",\"timestamp\":1508566174721},{\"args\":[\"android.os.Parcel$2@90f98cf\"],\"method\":\"invoke\",\"hooked_class\":\"java.util.Locale\",\"hooked_method\":\"readObject\",\"type\":\"reflection\",\"class\":\"java.lang.reflect.Method\",\"timestamp\":1508566163775},{\"args\":[\"android.os.Parcel$2@8dcf105\"],\"method\":\"invoke\",\"hooked_class\":\"java.util.Locale\",\"hooked_method\":\"readObject\",\"type\":\"reflection\",\"class\":\"java.lang.reflect.Method\",\"timestamp\":1508566163645},{\"args\":[\"android.os.Parcel$2@fed8c3f\"],\"method\":\"invoke\",\"hooked_class\":\"java.util.Locale\",\"hooked_method\":\"readObject\",\"type\":\"reflection\",\"class\":\"java.lang.reflect.Method\",\"timestamp\":1508566163697},{\"args\":[\"android.os.Parcel$2@d5e9954\"],\"method\":\"invoke\",\"hooked_class\":\"java.util.Locale\",\"hooked_method\":\"readObject\",\"type\":\"reflection\",\"class\":\"java.lang.reflect.Method\",\"timestamp\":1508566163812},{\"args\":[\"/data/user/0/digitalfish.counter/app_webview/webview_data.lock\",\"66\"],\"result\":{\"descriptor\":17},\"method\":\"open\",\"type\":\"file\",\"class\":\"libcore.io.IoBridge\",\"timestamp\":1508566162428},{\"args\":[\"org.chromium.net.NetworkChangeNotifierAutoDetect@885a5e7\",{\"mHasPartialTypes\":false,\"mPriority\":0,\"mActions\":[\"android.net.conn.CONNECTIVITY_CHANGE\"],\"mVerifyState\":0}],\"method\":\"registerReceiver\",\"type\":\"binder\",\"class\":\"android.app.ContextImpl\",\"timestamp\":1508566162594},{\"args\":[\"android.os.Parcel$2@526d6b9\"],\"method\":\"invoke\",\"hooked_class\":\"java.util.Locale\",\"hooked_method\":\"readObject\",\"type\":\"reflection\",\"class\":\"java.lang.reflect.Method\",\"timestamp\":1508566163658},{\"args\":[\"android.os.Parcel$2@8b74e57\"],\"method\":\"invoke\",\"hooked_class\":\"java.util.Locale\",\"hooked_method\":\"readObject\",\"type\":\"reflection\",\"class\":\"java.lang.reflect.Method\",\"timestamp\":1508566163672},{\"args\":[\"android.os.Parcel$2@7bf52e\"],\"method\":\"invoke\",\"hooked_class\":\"java.util.Locale\",\"hooked_method\":\"readObject\",\"type\":\"reflection\",\"class\":\"java.lang.reflect.Method\",\"timestamp\":1508566163774},{\"args\":[\"android.os.Parcel$2@9e49034\"],\"method\":\"invoke\",\"hooked_class\":\"java.util.Locale\",\"hooked_method\":\"readObject\",\"type\":\"reflection\",\"class\":\"java.lang.reflect.Method\",\"timestamp\":1508566163736},{\"args\":[\"android.os.Parcel$2@5c7ece2\"],\"method\":\"invoke\",\"hooked_class\":\"java.util.Locale\",\"hooked_method\":\"readObject\",\"type\":\"reflection\",\"class\":\"java.lang.reflect.Method\",\"timestamp\":1508566163771},{\"args\":[\"android.os.Parcel$2@b4d525c\"],\"method\":\"invoke\",\"hooked_class\":\"java.util.Locale\",\"hooked_method\":\"readObject\",\"type\":\"reflection\",\"class\":\"java.lang.reflect.Method\",\"timestamp\":1508566163776},{\"args\":[\"org.chromium.net.NetworkChangeNotifierAutoDetect@6b851fa\",{\"mHasPartialTypes\":false,\"mPriority\":0,\"mActions\":[\"android.net.conn.CONNECTIVITY_CHANGE\"],\"mVerifyState\":0}],\"method\":\"registerReceiver\",\"type\":\"binder\",\"class\":\"android.app.ContextImpl\",\"timestamp\":1508566162874},{\"args\":[\"android.os.Parcel$2@a264a00\"],\"method\":\"invoke\",\"hooked_class\":\"java.util.Locale\",\"hooked_method\":\"readObject\",\"type\":\"reflection\",\"class\":\"java.lang.reflect.Method\",\"timestamp\":1508566163761},{\"args\":[\"sClickingSoundVolume\",\"8\"],\"result\":{\"mClear\":false,\"mModified\":{\"sClickingSoundVolume\":8}},\"method\":\"putInt\",\"type\":\"globals\",\"class\":\"android.app.SharedPreferencesImpl$EditorImpl\",\"timestamp\":1508566191946},{\"args\":[\"sUseCount\",\"1\"],\"result\":{\"mClear\":false,\"mModified\":{\"sUseCount\":1,\"sMainCounterValue\":0}},\"method\":\"putInt\",\"type\":\"globals\",\"class\":\"android.app.SharedPreferencesImpl$EditorImpl\",\"timestamp\":1508566169866},{\"args\":[\"android.os.Parcel$2@c9f2927\"],\"method\":\"invoke\",\"hooked_class\":\"java.util.Locale\",\"hooked_method\":\"readObject\",\"type\":\"reflection\",\"class\":\"java.lang.reflect.Method\",\"timestamp\":1508566163713},{\"args\":[\"android.os.Parcel$2@9d446c2\"],\"method\":\"invoke\",\"hooked_class\":\"java.util.Locale\",\"hooked_method\":\"readObject\",\"type\":\"reflection\",\"class\":\"java.lang.reflect.Method\",\"timestamp\":1508566163704},{\"args\":[\"android.os.Parcel$2@26e6479\"],\"method\":\"invoke\",\"hooked_class\":\"java.util.Locale\",\"hooked_method\":\"readObject\",\"type\":\"reflection\",\"class\":\"java.lang.reflect.Method\",\"timestamp\":1508566163718},{\"args\":[\"android.os.Parcel$2@8e84ca3\"],\"method\":\"invoke\",\"hooked_class\":\"java.util.Locale\",\"hooked_method\":\"readObject\",\"type\":\"reflection\",\"class\":\"java.lang.reflect.Method\",\"timestamp\":1508566163738},{\"args\":[\"android.os.Parcel$2@7d77f7a\"],\"method\":\"invoke\",\"hooked_class\":\"java.util.Locale\",\"hooked_method\":\"readObject\",\"type\":\"reflection\",\"class\":\"java.lang.reflect.Method\",\"timestamp\":1508566163732},{\"args\":[\"android.os.Parcel$2@117b9b0\"],\"method\":\"invoke\",\"hooked_class\":\"java.util.Locale\",\"hooked_method\":\"readObject\",\"type\":\"reflection\",\"class\":\"java.lang.reflect.Method\",\"timestamp\":1508566163678},{\"args\":[\"android.os.Parcel$2@dc22599\"],\"method\":\"invoke\",\"hooked_class\":\"java.util.Locale\",\"hooked_method\":\"readObject\",\"type\":\"reflection\",\"class\":\"java.lang.reflect.Method\",\"timestamp\":1508566163696},{\"args\":[\"android.os.Parcel$2@ac8a1ea\"],\"method\":\"invoke\",\"hooked_class\":\"java.util.Locale\",\"hooked_method\":\"readObject\",\"type\":\"reflection\",\"class\":\"java.lang.reflect.Method\",\"timestamp\":1508566163788},{\"args\":[\"android.os.Parcel$2@a04ff84\"],\"method\":\"invoke\",\"hooked_class\":\"java.util.Locale\",\"hooked_method\":\"readObject\",\"type\":\"reflection\",\"class\":\"java.lang.reflect.Method\",\"timestamp\":1508566163831},{\"args\":[\"android.os.Parcel$2@34abb1c\"],\"method\":\"invoke\",\"hooked_class\":\"java.util.Locale\",\"hooked_method\":\"readObject\",\"type\":\"reflection\",\"class\":\"java.lang.reflect.Method\",\"timestamp\":1508566163841},{\"args\":[\"android.os.Parcel$2@7a87aa8\"],\"method\":\"invoke\",\"hooked_class\":\"java.util.Locale\",\"hooked_method\":\"readObject\",\"type\":\"reflection\",\"class\":\"java.lang.reflect.Method\",\"timestamp\":1508566163807},{\"args\":[\"chbClickSound\",\"true\"],\"result\":{\"mClear\":false,\"mModified\":{\"chbClickSound\":true}},\"method\":\"putBoolean\",\"type\":\"globals\",\"class\":\"android.app.SharedPreferencesImpl$EditorImpl\",\"timestamp\":1508566191937},{\"args\":[\"android.os.Parcel$2@8936d7d\"],\"method\":\"invoke\",\"hooked_class\":\"java.util.Locale\",\"hooked_method\":\"readObject\",\"type\":\"reflection\",\"class\":\"java.lang.reflect.Method\",\"timestamp\":1508566163715},{\"args\":[\"android.os.Parcel$2@d087512\"],\"method\":\"invoke\",\"hooked_class\":\"java.util.Locale\",\"hooked_method\":\"readObject\",\"type\":\"reflection\",\"class\":\"java.lang.reflect.Method\",\"timestamp\":1508566163694},{\"args\":[\"android.os.Parcel$2@4896a8d\"],\"method\":\"invoke\",\"hooked_class\":\"java.util.Locale\",\"hooked_method\":\"readObject\",\"type\":\"reflection\",\"class\":\"java.lang.reflect.Method\",\"timestamp\":1508566163794},{\"args\":[\"android.os.Parcel$2@1f4a32b\"],\"method\":\"invoke\",\"hooked_class\":\"java.util.Locale\",\"hooked_method\":\"readObject\",\"type\":\"reflection\",\"class\":\"java.lang.reflect.Method\",\"timestamp\":1508566163732},{\"args\":[{\"mDebugUnregister\":false},{\"mHasPartialTypes\":false,\"mPriority\":0,\"mActions\":[\"android.intent.action.PROXY_CHANGE\"],\"mVerifyState\":0}],\"method\":\"registerReceiver\",\"type\":\"binder\",\"class\":\"android.app.ContextImpl\",\"timestamp\":1508566162557},{\"args\":[\"android.os.Parcel$2@287da4\"],\"method\":\"invoke\",\"hooked_class\":\"java.util.Locale\",\"hooked_method\":\"readObject\",\"type\":\"reflection\",\"class\":\"java.lang.reflect.Method\",\"timestamp\":1508566163703},{\"args\":[\"android.os.Parcel$2@dcfe472\"],\"method\":\"invoke\",\"hooked_class\":\"java.util.Locale\",\"hooked_method\":\"readObject\",\"type\":\"reflection\",\"class\":\"java.lang.reflect.Method\",\"timestamp\":1508566163716},{\"args\":[\"sisDoNotShowAgainRateDialog\",\"false\"],\"result\":{\"mClear\":false,\"mModified\":{\"sisDoNotShowAgainRateDialog\":false,\"sMainCounterValue\":0,\"sUseCount\":1,\"sAwake\":false,\"sShowInstructions\":true}},\"method\":\"putBoolean\",\"type\":\"globals\",\"class\":\"android.app.SharedPreferencesImpl$EditorImpl\",\"timestamp\":1508566162906},{\"args\":[\"android.os.Parcel$2@1984707\"],\"method\":\"invoke\",\"hooked_class\":\"java.util.Locale\",\"hooked_method\":\"readObject\",\"type\":\"reflection\",\"class\":\"java.lang.reflect.Method\",\"timestamp\":1508566163735},{\"args\":[\"sMainCounterValue\",\"0\"],\"result\":{\"mClear\":false,\"mModified\":{\"sMainCounterValue\":0}},\"method\":\"putInt\",\"type\":\"globals\",\"class\":\"android.app.SharedPreferencesImpl$EditorImpl\",\"timestamp\":1508566169865},{\"args\":[\"android.os.Parcel$2@8fafff7\"],\"method\":\"invoke\",\"hooked_class\":\"java.util.Locale\",\"hooked_method\":\"readObject\",\"type\":\"reflection\",\"class\":\"java.lang.reflect.Method\",\"timestamp\":1508566163746},{\"args\":[\"android.os.Parcel$2@8fd6cd3\"],\"method\":\"invoke\",\"hooked_class\":\"java.util.Locale\",\"hooked_method\":\"readObject\",\"type\":\"reflection\",\"class\":\"java.lang.reflect.Method\",\"timestamp\":1508566163705},{\"args\":[\"android.os.Parcel$2@235491\"],\"method\":\"invoke\",\"hooked_class\":\"java.util.Locale\",\"hooked_method\":\"readObject\",\"type\":\"reflection\",\"class\":\"java.lang.reflect.Method\",\"timestamp\":1508566163745},{\"args\":[\"sisDoNotShowAgainRateDialog\",\"false\"],\"result\":{\"mClear\":false,\"mModified\":{\"sisDoNotShowAgainRateDialog\":false,\"sMainCounterValue\":0,\"sUseCount\":1,\"sAwake\":false,\"sShowInstructions\":true}},\"method\":\"putBoolean\",\"type\":\"globals\",\"class\":\"android.app.SharedPreferencesImpl$EditorImpl\",\"timestamp\":1508566183578},{\"args\":[\"android.os.Parcel$2@749d0b3\"],\"method\":\"invoke\",\"hooked_class\":\"java.util.Locale\",\"hooked_method\":\"readObject\",\"type\":\"reflection\",\"class\":\"java.lang.reflect.Method\",\"timestamp\":1508566163727},{\"args\":[\"android.os.Parcel$2@e639359\"],\"method\":\"invoke\",\"hooked_class\":\"java.util.Locale\",\"hooked_method\":\"readObject\",\"type\":\"reflection\",\"class\":\"java.lang.reflect.Method\",\"timestamp\":1508566163739},{\"args\":[\"android.os.Parcel$2@9ae9ba9\"],\"method\":\"invoke\",\"hooked_class\":\"java.util.Locale\",\"hooked_method\":\"readObject\",\"type\":\"reflection\",\"class\":\"java.lang.reflect.Method\",\"timestamp\":1508566163774},{\"args\":[\"android.os.Parcel$2@5769670\"],\"method\":\"invoke\",\"hooked_class\":\"java.util.Locale\",\"hooked_method\":\"readObject\",\"type\":\"reflection\",\"class\":\"java.lang.reflect.Method\",\"timestamp\":1508566163728},{\"args\":[\"android.os.Parcel$2@30bfafe\"],\"method\":\"invoke\",\"hooked_class\":\"java.util.Locale\",\"hooked_method\":\"readObject\",\"type\":\"reflection\",\"class\":\"java.lang.reflect.Method\",\"timestamp\":1508566163658},{\"args\":[\"android.os.Parcel$2@7eb130b\"],\"method\":\"invoke\",\"hooked_class\":\"java.util.Locale\",\"hooked_method\":\"readObject\",\"type\":\"reflection\",\"class\":\"java.lang.reflect.Method\",\"timestamp\":1508566163754},{\"args\":[\"android.os.Parcel$2@917a8cd\"],\"method\":\"invoke\",\"hooked_class\":\"java.util.Locale\",\"hooked_method\":\"readObject\",\"type\":\"reflection\",\"class\":\"java.lang.reflect.Method\",\"timestamp\":1508566163748},{\"args\":[\"/data/data/com.devadvance.rootcloak2/shared_prefs/CustomizeKeywords.xml\",\"0\"],\"result\":{\"descriptor\":16},\"method\":\"open\",\"type\":\"file\",\"class\":\"libcore.io.IoBridge\",\"timestamp\":1508566162314},{\"args\":[\"android.os.Parcel$2@27878f3\"],\"method\":\"invoke\",\"hooked_class\":\"java.util.Locale\",\"hooked_method\":\"readObject\",\"type\":\"reflection\",\"class\":\"java.lang.reflect.Method\",\"timestamp\":1508566163677},{\"args\":[\"android.os.Parcel$2@c02de96\"],\"method\":\"invoke\",\"hooked_class\":\"java.util.Locale\",\"hooked_method\":\"readObject\",\"type\":\"reflection\",\"class\":\"java.lang.reflect.Method\",\"timestamp\":1508566163724},{\"args\":[\"android.os.Parcel$2@fb18401\"],\"method\":\"invoke\",\"hooked_class\":\"java.util.Locale\",\"hooked_method\":\"readObject\",\"type\":\"reflection\",\"class\":\"java.lang.reflect.Method\",\"timestamp\":1508566163756},{\"args\":[\"android.os.Parcel$2@d22c388\"],\"method\":\"invoke\",\"hooked_class\":\"java.util.Locale\",\"hooked_method\":\"readObject\",\"type\":\"reflection\",\"class\":\"java.lang.reflect.Method\",\"timestamp\":1508566163733},{\"args\":[\"chbSpeakingCounter\",\"false\"],\"result\":{\"mClear\":false,\"mModified\":{\"chbSpeakingCounter\":false}},\"method\":\"putBoolean\",\"type\":\"globals\",\"class\":\"android.app.SharedPreferencesImpl$EditorImpl\",\"timestamp\":1508566191935},{\"args\":[\"gsm.operator.iso-country\"],\"result\":\"\",\"method\":\"get\",\"type\":\"content\",\"class\":\"android.os.SystemProperties\",\"timestamp\":1508566162699},{\"args\":[\"sShowInstructions\",\"true\"],\"result\":{\"mClear\":false,\"mModified\":{\"sUseCount\":1,\"sMainCounterValue\":0,\"sAwake\":false,\"sShowInstructions\":true}},\"method\":\"putBoolean\",\"type\":\"globals\",\"class\":\"android.app.SharedPreferencesImpl$EditorImpl\",\"timestamp\":1508566169869},{\"args\":[\"persist.sys.timezone\"],\"result\":\"America/New_York\",\"method\":\"get\",\"type\":\"content\",\"class\":\"android.os.SystemProperties\",\"timestamp\":1508566162501},{\"args\":[\"android.os.Parcel$2@417b14f\"],\"method\":\"invoke\",\"hooked_class\":\"java.util.Locale\",\"hooked_method\":\"readObject\",\"type\":\"reflection\",\"class\":\"java.lang.reflect.Method\",\"timestamp\":1508566163686},{\"args\":[\"/data/user/0/digitalfish.counter/shared_prefs/digitalfish.counter_preferences.xml\",\"577\"],\"result\":{\"descriptor\":53},\"method\":\"open\",\"type\":\"file\",\"class\":\"libcore.io.IoBridge\",\"timestamp\":1508566191979},{\"args\":[\"android.os.Parcel$2@a5bdd3c\"],\"method\":\"invoke\",\"hooked_class\":\"java.util.Locale\",\"hooked_method\":\"readObject\",\"type\":\"reflection\",\"class\":\"java.lang.reflect.Method\",\"timestamp\":1508566163708},{\"args\":[\"sShowInstructions\",\"true\"],\"result\":{\"mClear\":false,\"mModified\":{\"sUseCount\":1,\"sMainCounterValue\":0,\"sAwake\":false,\"sShowInstructions\":true}},\"method\":\"putBoolean\",\"type\":\"globals\",\"class\":\"android.app.SharedPreferencesImpl$EditorImpl\",\"timestamp\":1508566183577},{\"args\":[\"android.os.Parcel$2@94f25fc\"],\"method\":\"invoke\",\"hooked_class\":\"java.util.Locale\",\"hooked_method\":\"readObject\",\"type\":\"reflection\",\"class\":\"java.lang.reflect.Method\",\"timestamp\":1508566163752},{\"args\":[\"android.os.Parcel$2@9dad57b\"],\"method\":\"invoke\",\"hooked_class\":\"java.util.Locale\",\"hooked_method\":\"readObject\",\"type\":\"reflection\",\"class\":\"java.lang.reflect.Method\",\"timestamp\":1508566163663},{\"args\":[\"android.os.Parcel$2@938ad5b\"],\"method\":\"invoke\",\"hooked_class\":\"java.util.Locale\",\"hooked_method\":\"readObject\",\"type\":\"reflection\",\"class\":\"java.lang.reflect.Method\",\"timestamp\":1508566163700},{\"args\":[\"android.os.Parcel$2@a864e22\"],\"method\":\"invoke\",\"hooked_class\":\"java.util.Locale\",\"hooked_method\":\"readObject\",\"type\":\"reflection\",\"class\":\"java.lang.reflect.Method\",\"timestamp\":1508566163726},{\"args\":[\"webviewchromium_plat_support\"],\"result\":\"/system/lib/libwebviewchromium_plat_support.so\",\"method\":\"findLibrary\",\"type\":\"dex\",\"class\":\"dalvik.system.BaseDexClassLoader\",\"timestamp\":1508566162353},{\"args\":[\"android.os.Parcel$2@f06c50f\"],\"method\":\"invoke\",\"hooked_class\":\"java.util.Locale\",\"hooked_method\":\"readObject\",\"type\":\"reflection\",\"class\":\"java.lang.reflect.Method\",\"timestamp\":1508566163730},{\"args\":[\"android.os.Parcel$2@d087a51\"],\"method\":\"invoke\",\"hooked_class\":\"java.util.Locale\",\"hooked_method\":\"readObject\",\"type\":\"reflection\",\"class\":\"java.lang.reflect.Method\",\"timestamp\":1508566163790},{\"args\":[\"android.os.Parcel$2@290e121\"],\"method\":\"invoke\",\"hooked_class\":\"java.util.Locale\",\"hooked_method\":\"readObject\",\"type\":\"reflection\",\"class\":\"java.lang.reflect.Method\",\"timestamp\":1508566163734},{\"args\":[\"android.os.Parcel$2@e97ec1a\"],\"method\":\"invoke\",\"hooked_class\":\"java.util.Locale\",\"hooked_method\":\"readObject\",\"type\":\"reflection\",\"class\":\"java.lang.reflect.Method\",\"timestamp\":1508566163710},{\"args\":[\"android.os.Parcel$2@e2c4965\"],\"method\":\"invoke\",\"hooked_class\":\"java.util.Locale\",\"hooked_method\":\"readObject\",\"type\":\"reflection\",\"class\":\"java.lang.reflect.Method\",\"timestamp\":1508566163776},{\"args\":[\"android.os.Parcel$2@a14707e\"],\"method\":\"invoke\",\"hooked_class\":\"java.util.Locale\",\"hooked_method\":\"readObject\",\"type\":\"reflection\",\"class\":\"java.lang.reflect.Method\",\"timestamp\":1508566163763},{\"args\":[\"android.os.Parcel$2@226161f\"],\"method\":\"invoke\",\"hooked_class\":\"java.util.Locale\",\"hooked_method\":\"readObject\",\"type\":\"reflection\",\"class\":\"java.lang.reflect.Method\",\"timestamp\":1508566163719},{\"args\":[\"android.os.Parcel$2@9d27b47\"],\"method\":\"invoke\",\"hooked_class\":\"java.util.Locale\",\"hooked_method\":\"readObject\",\"type\":\"reflection\",\"class\":\"java.lang.reflect.Method\",\"timestamp\":1508566163692},{\"args\":[\"android.os.Parcel$2@615b1cc\"],\"method\":\"invoke\",\"hooked_class\":\"java.util.Locale\",\"hooked_method\":\"readObject\",\"type\":\"reflection\",\"class\":\"java.lang.reflect.Method\",\"timestamp\":1508566163742},{\"args\":[\"org.chromium.net.NetworkChangeNotifierAutoDetect@6b851fa\",{\"mHasPartialTypes\":false,\"mPriority\":0,\"mActions\":[\"android.net.conn.CONNECTIVITY_CHANGE\"],\"mVerifyState\":0}],\"method\":\"registerReceiver\",\"type\":\"binder\",\"class\":\"android.app.ContextImpl\",\"timestamp\":1508566162795},{\"args\":[\"android.os.Parcel$2@2603330\"],\"method\":\"invoke\",\"hooked_class\":\"java.util.Locale\",\"hooked_method\":\"readObject\",\"type\":\"reflection\",\"class\":\"java.lang.reflect.Method\",\"timestamp\":1508566163773},{\"args\":[\"android.os.Parcel$2@f7c6325\"],\"method\":\"invoke\",\"hooked_class\":\"java.util.Locale\",\"hooked_method\":\"readObject\",\"type\":\"reflection\",\"class\":\"java.lang.reflect.Method\",\"timestamp\":1508566163843},{\"args\":[\"org.chromium.net.NetworkChangeNotifierAutoDetect@885a5e7\",{\"mHasPartialTypes\":false,\"mPriority\":0,\"mActions\":[\"android.net.conn.CONNECTIVITY_CHANGE\"],\"mVerifyState\":0}],\"method\":\"registerReceiver\",\"type\":\"binder\",\"class\":\"android.app.ContextImpl\",\"timestamp\":1508566162639},{\"args\":[\"android.os.Parcel$2@3078442\"],\"method\":\"invoke\",\"hooked_class\":\"java.util.Locale\",\"hooked_method\":\"readObject\",\"type\":\"reflection\",\"class\":\"java.lang.reflect.Method\",\"timestamp\":1508566163795},{\"args\":[\"android.os.Parcel$2@416f2eb\"],\"method\":\"invoke\",\"hooked_class\":\"java.util.Locale\",\"hooked_method\":\"readObject\",\"type\":\"reflection\",\"class\":\"java.lang.reflect.Method\",\"timestamp\":1508566163778},{\"args\":[\"android.os.Parcel$2@9efd2c7\"],\"method\":\"invoke\",\"hooked_class\":\"java.util.Locale\",\"hooked_method\":\"readObject\",\"type\":\"reflection\",\"class\":\"java.lang.reflect.Method\",\"timestamp\":1508566163781},{\"args\":[\"android.os.Parcel$2@b759ec6\"],\"method\":\"invoke\",\"hooked_class\":\"java.util.Locale\",\"hooked_method\":\"readObject\",\"type\":\"reflection\",\"class\":\"java.lang.reflect.Method\",\"timestamp\":1508566163849},{\"args\":[\"android.os.Parcel$2@ef710fd\"],\"method\":\"invoke\",\"hooked_class\":\"java.util.Locale\",\"hooked_method\":\"readObject\",\"type\":\"reflection\",\"class\":\"java.lang.reflect.Method\",\"timestamp\":1508566163813},{\"args\":[\"android.os.Parcel$2@e350d44\"],\"method\":\"invoke\",\"hooked_class\":\"java.util.Locale\",\"hooked_method\":\"readObject\",\"type\":\"reflection\",\"class\":\"java.lang.reflect.Method\",\"timestamp\":1508566163673},{\"args\":[\"android.os.Parcel$2@7b5f6c0\"],\"method\":\"invoke\",\"hooked_class\":\"java.util.Locale\",\"hooked_method\":\"readObject\",\"type\":\"reflection\",\"class\":\"java.lang.reflect.Method\",\"timestamp\":1508566163817},{\"args\":[\"android.os.Parcel$2@d398e2d\"],\"method\":\"invoke\",\"hooked_class\":\"java.util.Locale\",\"hooked_method\":\"readObject\",\"type\":\"reflection\",\"class\":\"java.lang.reflect.Method\",\"timestamp\":1508566163675},{\"args\":[\"android.os.Parcel$2@d450990\"],\"method\":\"invoke\",\"hooked_class\":\"java.util.Locale\",\"hooked_method\":\"readObject\",\"type\":\"reflection\",\"class\":\"java.lang.reflect.Method\",\"timestamp\":1508566163797},{\"args\":[\"android.os.Parcel$2@e13336d\"],\"method\":\"invoke\",\"hooked_class\":\"java.util.Locale\",\"hooked_method\":\"readObject\",\"type\":\"reflection\",\"class\":\"java.lang.reflect.Method\",\"timestamp\":1508566163833},{\"args\":[\"android.os.Parcel$2@155b9f8\"],\"method\":\"invoke\",\"hooked_class\":\"java.util.Locale\",\"hooked_method\":\"readObject\",\"type\":\"reflection\",\"class\":\"java.lang.reflect.Method\",\"timestamp\":1508566163700},{\"args\":[\"android.os.Parcel$2@b0eaa17\"],\"method\":\"invoke\",\"hooked_class\":\"java.util.Locale\",\"hooked_method\":\"readObject\",\"type\":\"reflection\",\"class\":\"java.lang.reflect.Method\",\"timestamp\":1508566163724},{\"args\":[\"android.os.Parcel$2@1db9e04\"],\"method\":\"invoke\",\"hooked_class\":\"java.util.Locale\",\"hooked_method\":\"readObject\",\"type\":\"reflection\",\"class\":\"java.lang.reflect.Method\",\"timestamp\":1508566163725},{\"args\":[\"android.os.Parcel$2@e86a99c\"],\"method\":\"invoke\",\"hooked_class\":\"java.util.Locale\",\"hooked_method\":\"readObject\",\"type\":\"reflection\",\"class\":\"java.lang.reflect.Method\",\"timestamp\":1508566163730},{\"args\":[\"android.os.Parcel$2@df9eed1\"],\"method\":\"invoke\",\"hooked_class\":\"java.util.Locale\",\"hooked_method\":\"readObject\",\"type\":\"reflection\",\"class\":\"java.lang.reflect.Method\",\"timestamp\":1508566163701},{\"args\":[\"android.os.Parcel$2@da6062c\"],\"method\":\"invoke\",\"hooked_class\":\"java.util.Locale\",\"hooked_method\":\"readObject\",\"type\":\"reflection\",\"class\":\"java.lang.reflect.Method\",\"timestamp\":1508566163764},{\"args\":[\"sAwake\",\"false\"],\"result\":{\"mClear\":false,\"mModified\":{\"sUseCount\":1,\"sMainCounterValue\":0,\"sAwake\":false}},\"method\":\"putBoolean\",\"type\":\"globals\",\"class\":\"android.app.SharedPreferencesImpl$EditorImpl\",\"timestamp\":1508566183575},{\"args\":[\"android.os.Parcel$2@88304c9\"],\"method\":\"invoke\",\"hooked_class\":\"java.util.Locale\",\"hooked_method\":\"readObject\",\"type\":\"reflection\",\"class\":\"java.lang.reflect.Method\",\"timestamp\":1508566163750},{\"args\":[\"sShowInstructions\",\"true\"],\"result\":{\"mClear\":false,\"mModified\":{\"sUseCount\":1,\"sMainCounterValue\":0,\"sAwake\":false,\"sShowInstructions\":true}},\"method\":\"putBoolean\",\"type\":\"globals\",\"class\":\"android.app.SharedPreferencesImpl$EditorImpl\",\"timestamp\":1508566174729},{\"args\":[\"sAwake\",\"false\"],\"result\":{\"mClear\":false,\"mModified\":{\"sUseCount\":1,\"sMainCounterValue\":0,\"sAwake\":false}},\"method\":\"putBoolean\",\"type\":\"globals\",\"class\":\"android.app.SharedPreferencesImpl$EditorImpl\",\"timestamp\":1508566162903},{\"args\":[\"android.os.Parcel$2@bab3c68\"],\"method\":\"invoke\",\"hooked_class\":\"java.util.Locale\",\"hooked_method\":\"readObject\",\"type\":\"reflection\",\"class\":\"java.lang.reflect.Method\",\"timestamp\":1508566163650},{\"args\":[\"android.os.Parcel$2@a4283d2\"],\"method\":\"invoke\",\"hooked_class\":\"java.util.Locale\",\"hooked_method\":\"readObject\",\"type\":\"reflection\",\"class\":\"java.lang.reflect.Method\",\"timestamp\":1508566163737},{\"args\":[\"android.os.Parcel$2@ff45de9\"],\"method\":\"invoke\",\"hooked_class\":\"java.util.Locale\",\"hooked_method\":\"readObject\",\"type\":\"reflection\",\"class\":\"java.lang.reflect.Method\",\"timestamp\":1508566163728},{\"args\":[\"android.os.Parcel$2@61d91ad\"],\"method\":\"invoke\",\"hooked_class\":\"java.util.Locale\",\"hooked_method\":\"readObject\",\"type\":\"reflection\",\"class\":\"java.lang.reflect.Method\",\"timestamp\":1508566163770},{\"args\":[\"android.os.Parcel$2@b4b30c3\"],\"method\":\"invoke\",\"hooked_class\":\"java.util.Locale\",\"hooked_method\":\"readObject\",\"type\":\"reflection\",\"class\":\"java.lang.reflect.Method\",\"timestamp\":1508566163716},{\"args\":[\"android.os.Parcel$2@bd66d08\"],\"method\":\"invoke\",\"hooked_class\":\"java.util.Locale\",\"hooked_method\":\"readObject\",\"type\":\"reflection\",\"class\":\"java.lang.reflect.Method\",\"timestamp\":1508566163846},{\"args\":[\"android.os.Parcel$2@3dd3bbd\"],\"method\":\"invoke\",\"hooked_class\":\"java.util.Locale\",\"hooked_method\":\"readObject\",\"type\":\"reflection\",\"class\":\"java.lang.reflect.Method\",\"timestamp\":1508566163654},{\"args\":[\"android.os.Parcel$2@8d9b239\"],\"method\":\"invoke\",\"hooked_class\":\"java.util.Locale\",\"hooked_method\":\"readObject\",\"type\":\"reflection\",\"class\":\"java.lang.reflect.Method\",\"timestamp\":1508566163762},{\"args\":[\"android.os.Parcel$2@46e79df\"],\"method\":\"invoke\",\"hooked_class\":\"java.util.Locale\",\"hooked_method\":\"readObject\",\"type\":\"reflection\",\"class\":\"java.lang.reflect.Method\",\"timestamp\":1508566163764},{\"args\":[\"lastVersionCodeUsed\",\"316309800\"],\"result\":{\"mClear\":false,\"mModified\":{\"lastVersionCodeUsed\":316309800}},\"method\":\"putInt\",\"type\":\"globals\",\"class\":\"android.app.SharedPreferencesImpl$EditorImpl\",\"timestamp\":1508566162374},{\"args\":[\"android.os.Parcel$2@7b15f3d\"],\"method\":\"invoke\",\"hooked_class\":\"java.util.Locale\",\"hooked_method\":\"readObject\",\"type\":\"reflection\",\"class\":\"java.lang.reflect.Method\",\"timestamp\":1508566163759},{\"args\":[\"android.os.Parcel$2@5f75d4a\"],\"method\":\"invoke\",\"hooked_class\":\"java.util.Locale\",\"hooked_method\":\"readObject\",\"type\":\"reflection\",\"class\":\"java.lang.reflect.Method\",\"timestamp\":1508566163824},{\"args\":[\"android.os.Parcel$2@a475c9d\"],\"method\":\"invoke\",\"hooked_class\":\"java.util.Locale\",\"hooked_method\":\"readObject\",\"type\":\"reflection\",\"class\":\"java.lang.reflect.Method\",\"timestamp\":1508566163693},{\"args\":[\"android.os.Parcel$2@388ad1b\"],\"method\":\"invoke\",\"hooked_class\":\"java.util.Locale\",\"hooked_method\":\"readObject\",\"type\":\"reflection\",\"class\":\"java.lang.reflect.Method\",\"timestamp\":1508566163744},{\"args\":[\"android.os.Parcel$2@7b85332\"],\"method\":\"invoke\",\"hooked_class\":\"java.util.Locale\",\"hooked_method\":\"readObject\",\"type\":\"reflection\",\"class\":\"java.lang.reflect.Method\",\"timestamp\":1508566163759},{\"args\":[\"android.os.Parcel$2@56363a\"],\"method\":\"invoke\",\"hooked_class\":\"java.util.Locale\",\"hooked_method\":\"readObject\",\"type\":\"reflection\",\"class\":\"java.lang.reflect.Method\",\"timestamp\":1508566163777},{\"args\":[\"android.os.Parcel$2@1538fca\"],\"method\":\"invoke\",\"hooked_class\":\"java.util.Locale\",\"hooked_method\":\"readObject\",\"type\":\"reflection\",\"class\":\"java.lang.reflect.Method\",\"timestamp\":1508566163721},{\"args\":[\"/proc/meminfo\",\"0\"],\"result\":{\"descriptor\":20},\"method\":\"open\",\"type\":\"file\",\"class\":\"libcore.io.IoBridge\",\"timestamp\":1508566162497},{\"args\":[\"android.os.Parcel$2@e9435b2\"],\"method\":\"invoke\",\"hooked_class\":\"java.util.Locale\",\"hooked_method\":\"readObject\",\"type\":\"reflection\",\"class\":\"java.lang.reflect.Method\",\"timestamp\":1508566163655},{\"args\":[\"android.os.Parcel$2@85b55d5\"],\"method\":\"invoke\",\"hooked_class\":\"java.util.Locale\",\"hooked_method\":\"readObject\",\"type\":\"reflection\",\"class\":\"java.lang.reflect.Method\",\"timestamp\":1508566163787},{\"args\":[\"gsm.operator.iso-country\"],\"result\":\"\",\"method\":\"get\",\"type\":\"content\",\"class\":\"android.os.SystemProperties\",\"timestamp\":1508566162673},{\"args\":[\"android.os.Parcel$2@207c5d7\"],\"method\":\"invoke\",\"hooked_class\":\"java.util.Locale\",\"hooked_method\":\"readObject\",\"type\":\"reflection\",\"class\":\"java.lang.reflect.Method\",\"timestamp\":1508566163769},{\"args\":[\"android.os.Parcel$2@948ff0\"],\"method\":\"invoke\",\"hooked_class\":\"java.util.Locale\",\"hooked_method\":\"readObject\",\"type\":\"reflection\",\"class\":\"java.lang.reflect.Method\",\"timestamp\":1508566163836},{\"args\":[\"android.os.Parcel$2@6bc9969\"],\"method\":\"invoke\",\"hooked_class\":\"java.util.Locale\",\"hooked_method\":\"readObject\",\"type\":\"reflection\",\"class\":\"java.lang.reflect.Method\",\"timestamp\":1508566163838},{\"args\":[\"android.os.Parcel$2@5759458\"],\"method\":\"invoke\",\"hooked_class\":\"java.util.Locale\",\"hooked_method\":\"readObject\",\"type\":\"reflection\",\"class\":\"java.lang.reflect.Method\",\"timestamp\":1508566163722},{\"args\":[\"android.os.Parcel$2@4c09881\"],\"method\":\"invoke\",\"hooked_class\":\"java.util.Locale\",\"hooked_method\":\"readObject\",\"type\":\"reflection\",\"class\":\"java.lang.reflect.Method\",\"timestamp\":1508566163651},{\"args\":[{\"mDebugUnregister\":false},{\"mHasPartialTypes\":false,\"mPriority\":0,\"mActions\":[\"android.intent.action.USER_PRESENT\",\"android.intent.action.SCREEN_OFF\"],\"mVerifyState\":0}],\"method\":\"registerReceiver\",\"type\":\"binder\",\"class\":\"android.app.ContextImpl\",\"timestamp\":1508566162709},{\"args\":[\"android.os.Parcel$2@763beec\"],\"method\":\"invoke\",\"hooked_class\":\"java.util.Locale\",\"hooked_method\":\"readObject\",\"type\":\"reflection\",\"class\":\"java.lang.reflect.Method\",\"timestamp\":1508566163822},{\"args\":[\"ro.config.low_ram\",\"false\"],\"result\":\"false\",\"method\":\"get\",\"type\":\"content\",\"class\":\"android.os.SystemProperties\",\"timestamp\":1508566162147},{\"args\":[\"android.os.Parcel$2@228bff9\"],\"method\":\"invoke\",\"hooked_class\":\"java.util.Locale\",\"hooked_method\":\"readObject\",\"type\":\"reflection\",\"class\":\"java.lang.reflect.Method\",\"timestamp\":1508566163818},{\"args\":[\"android.os.Parcel$2@12e2485\"],\"method\":\"invoke\",\"hooked_class\":\"java.util.Locale\",\"hooked_method\":\"readObject\",\"type\":\"reflection\",\"class\":\"java.lang.reflect.Method\",\"timestamp\":1508566163753},{\"args\":[\"ro.config.low_ram\",\"false\"],\"result\":\"false\",\"method\":\"get\",\"type\":\"content\",\"class\":\"android.os.SystemProperties\",\"timestamp\":1508566162146},{\"args\":[\"android.os.Parcel$2@7b5d4e7\"],\"method\":\"invoke\",\"hooked_class\":\"java.util.Locale\",\"hooked_method\":\"readObject\",\"type\":\"reflection\",\"class\":\"java.lang.reflect.Method\",\"timestamp\":1508566163757},{\"args\":[\"/data/user/0/digitalfish.counter/shared_prefs/digitalfish.counter_preferences.xml\",\"577\"],\"result\":{\"descriptor\":53},\"method\":\"open\",\"type\":\"file\",\"class\":\"libcore.io.IoBridge\",\"timestamp\":1508566191953},{\"args\":[\"ro.config.low_ram\",\"false\"],\"result\":\"false\",\"method\":\"get\",\"type\":\"content\",\"class\":\"android.os.SystemProperties\",\"timestamp\":1508566162150},{\"args\":[\"sShowInstructions\",\"true\"],\"result\":{\"mClear\":false,\"mModified\":{\"sUseCount\":1,\"sMainCounterValue\":0,\"sAwake\":false,\"sShowInstructions\":true}},\"method\":\"putBoolean\",\"type\":\"globals\",\"class\":\"android.app.SharedPreferencesImpl$EditorImpl\",\"timestamp\":1508566162905},{\"args\":[\"android.os.Parcel$2@8ef02ab\"],\"method\":\"invoke\",\"hooked_class\":\"java.util.Locale\",\"hooked_method\":\"readObject\",\"type\":\"reflection\",\"class\":\"java.lang.reflect.Method\",\"timestamp\":1508566163845},{\"args\":[\"/data/user/0/digitalfish.counter/shared_prefs/digitalfish.counter_preferences.xml\",\"577\"],\"result\":{\"descriptor\":53},\"method\":\"open\",\"type\":\"file\",\"class\":\"libcore.io.IoBridge\",\"timestamp\":1508566191973},{\"args\":[],\"result\":\"\",\"method\":\"getNetworkCountryIso\",\"type\":\"fingerprint\",\"class\":\"android.telephony.TelephonyManager\",\"timestamp\":1508566162729},{\"args\":[\"debug.second-display.pkg\"],\"result\":\"\",\"method\":\"get\",\"type\":\"content\",\"class\":\"android.os.SystemProperties\",\"timestamp\":1508566174585},{\"args\":[\"android.os.Parcel$2@fcde029\"],\"method\":\"invoke\",\"hooked_class\":\"java.util.Locale\",\"hooked_method\":\"readObject\",\"type\":\"reflection\",\"class\":\"java.lang.reflect.Method\",\"timestamp\":1508566163684},{\"args\":[\"ro.config.low_ram\",\"false\"],\"result\":\"false\",\"method\":\"get\",\"type\":\"content\",\"class\":\"android.os.SystemProperties\",\"timestamp\":1508566162145},{\"args\":[\"/data/user/0/digitalfish.counter/shared_prefs/digitalfish.counter_preferences.xml\",\"577\"],\"result\":{\"descriptor\":53},\"method\":\"open\",\"type\":\"file\",\"class\":\"libcore.io.IoBridge\",\"timestamp\":1508566191937},{\"args\":[\"android.os.Parcel$2@5a26f71\"],\"method\":\"invoke\",\"hooked_class\":\"java.util.Locale\",\"hooked_method\":\"readObject\",\"type\":\"reflection\",\"class\":\"java.lang.reflect.Method\",\"timestamp\":1508566163768},{\"args\":[\"android.os.Parcel$2@1a90fff\"],\"method\":\"invoke\",\"hooked_class\":\"java.util.Locale\",\"hooked_method\":\"readObject\",\"type\":\"reflection\",\"class\":\"java.lang.reflect.Method\",\"timestamp\":1508566163741},{\"args\":[\"android.os.Parcel$2@7895292\"],\"method\":\"invoke\",\"hooked_class\":\"java.util.Locale\",\"hooked_method\":\"readObject\",\"type\":\"reflection\",\"class\":\"java.lang.reflect.Method\",\"timestamp\":1508566163783},{\"args\":[\"android.os.Parcel$2@729aaaf\"],\"method\":\"invoke\",\"hooked_class\":\"java.util.Locale\",\"hooked_method\":\"readObject\",\"type\":\"reflection\",\"class\":\"java.lang.reflect.Method\",\"timestamp\":1508566163801},{\"args\":[\"android.os.Parcel$2@9a190c\"],\"method\":\"invoke\",\"hooked_class\":\"java.util.Locale\",\"hooked_method\":\"readObject\",\"type\":\"reflection\",\"class\":\"java.lang.reflect.Method\",\"timestamp\":1508566163698},{\"args\":[\"android.os.Parcel$2@7b477ce\"],\"method\":\"invoke\",\"hooked_class\":\"java.util.Locale\",\"hooked_method\":\"readObject\",\"type\":\"reflection\",\"class\":\"java.lang.reflect.Method\",\"timestamp\":1508566163751},{\"args\":[\"android.os.Parcel$2@e3184e3\"],\"method\":\"invoke\",\"hooked_class\":\"java.util.Locale\",\"hooked_method\":\"readObject\",\"type\":\"reflection\",\"class\":\"java.lang.reflect.Method\",\"timestamp\":1508566163694},{\"args\":[\"android.os.Parcel$2@868255\"],\"method\":\"invoke\",\"hooked_class\":\"java.util.Locale\",\"hooked_method\":\"readObject\",\"type\":\"reflection\",\"class\":\"java.lang.reflect.Method\",\"timestamp\":1508566163698},{\"args\":[\"android.os.Parcel$2@5417fee\"],\"method\":\"invoke\",\"hooked_class\":\"java.util.Locale\",\"hooked_method\":\"readObject\",\"type\":\"reflection\",\"class\":\"java.lang.reflect.Method\",\"timestamp\":1508566163839},{\"args\":[\"sMainCounterValue\",\"0\"],\"result\":{\"mClear\":false,\"mModified\":{\"sMainCounterValue\":0}},\"method\":\"putInt\",\"type\":\"globals\",\"class\":\"android.app.SharedPreferencesImpl$EditorImpl\",\"timestamp\":1508566183570},{\"args\":[\"android.os.Parcel$2@918e873\"],\"method\":\"invoke\",\"hooked_class\":\"java.util.Locale\",\"hooked_method\":\"readObject\",\"type\":\"reflection\",\"class\":\"java.lang.reflect.Method\",\"timestamp\":1508566163772},{\"args\":[\"debug.second-display.pkg\"],\"result\":\"\",\"method\":\"get\",\"type\":\"content\",\"class\":\"android.os.SystemProperties\",\"timestamp\":1508566162137},{\"args\":[\"android.os.Parcel$2@e0b99c1\"],\"method\":\"invoke\",\"hooked_class\":\"java.util.Locale\",\"hooked_method\":\"readObject\",\"type\":\"reflection\",\"class\":\"java.lang.reflect.Method\",\"timestamp\":1508566163808},{\"args\":[\"android.os.Parcel$2@7506b61\"],\"method\":\"invoke\",\"hooked_class\":\"java.util.Locale\",\"hooked_method\":\"readObject\",\"type\":\"reflection\",\"class\":\"java.lang.reflect.Method\",\"timestamp\":1508566163690},{\"args\":[\"sUseCount\",\"1\"],\"result\":{\"mClear\":false,\"mModified\":{\"sUseCount\":1,\"sMainCounterValue\":0}},\"method\":\"putInt\",\"type\":\"globals\",\"class\":\"android.app.SharedPreferencesImpl$EditorImpl\",\"timestamp\":1508566174724},{\"args\":[\"android.os.Parcel$2@70d81f2\"],\"method\":\"invoke\",\"hooked_class\":\"java.util.Locale\",\"hooked_method\":\"readObject\",\"type\":\"reflection\",\"class\":\"java.lang.reflect.Method\",\"timestamp\":1508566163814},{\"args\":[\"android.os.Parcel$2@138afe6\"],\"method\":\"invoke\",\"hooked_class\":\"java.util.Locale\",\"hooked_method\":\"readObject\",\"type\":\"reflection\",\"class\":\"java.lang.reflect.Method\",\"timestamp\":1508566163713},{\"args\":[\"android.os.Parcel$2@6c8136b\"],\"method\":\"invoke\",\"hooked_class\":\"java.util.Locale\",\"hooked_method\":\"readObject\",\"type\":\"reflection\",\"class\":\"java.lang.reflect.Method\",\"timestamp\":1508566163689},{\"args\":[\"ro.config.low_ram\",\"false\"],\"result\":\"false\",\"method\":\"get\",\"type\":\"content\",\"class\":\"android.os.SystemProperties\",\"timestamp\":1508566191905},{\"args\":[\"android.os.Parcel$2@b3ec860\"],\"method\":\"invoke\",\"hooked_class\":\"java.util.Locale\",\"hooked_method\":\"readObject\",\"type\":\"reflection\",\"class\":\"java.lang.reflect.Method\",\"timestamp\":1508566163784},{\"args\":[\"/data/app/com.google.android.webview-1/base.apk\",\"/data/app/com.google.android.webview-1/lib/arm:/data/app/com.google.android.webview-1/base.apk!/lib/armeabi-v7a\",\"dalvik.system.PathClassLoader[DexPathList[[dex file \\\"/data/dalvik-cache/xposed_XResourcesSuperClass.dex\\\"],nativeLibraryDirectories=[/vendor/lib, /system/lib]]]\"],\"method\":\"dalvik.system.PathClassLoader\",\"type\":\"dex\",\"class\":\"dalvik.system.PathClassLoader\",\"timestamp\":1508566162307},{\"args\":[\"android.os.Parcel$2@3a442da\"],\"method\":\"invoke\",\"hooked_class\":\"java.util.Locale\",\"hooked_method\":\"readObject\",\"type\":\"reflection\",\"class\":\"java.lang.reflect.Method\",\"timestamp\":1508566163754},{\"args\":[\"android.os.Parcel$2@dbe6cdb\"],\"method\":\"invoke\",\"hooked_class\":\"java.util.Locale\",\"hooked_method\":\"readObject\",\"type\":\"reflection\",\"class\":\"java.lang.reflect.Method\",\"timestamp\":1508566163789},{\"args\":[\"android.os.Parcel$2@97897d4\"],\"method\":\"invoke\",\"hooked_class\":\"java.util.Locale\",\"hooked_method\":\"readObject\",\"type\":\"reflection\",\"class\":\"java.lang.reflect.Method\",\"timestamp\":1508566163714},{\"args\":[\"android.os.Parcel$2@6841156\"],\"method\":\"invoke\",\"hooked_class\":\"java.util.Locale\",\"hooked_method\":\"readObject\",\"type\":\"reflection\",\"class\":\"java.lang.reflect.Method\",\"timestamp\":1508566163768},{\"args\":[\"android.os.Parcel$2@1f22c8f\"],\"method\":\"invoke\",\"hooked_class\":\"java.util.Locale\",\"hooked_method\":\"readObject\",\"type\":\"reflection\",\"class\":\"java.lang.reflect.Method\",\"timestamp\":1508566163840},{\"args\":[\"android.os.Parcel$2@fbfafed\"],\"method\":\"invoke\",\"hooked_class\":\"java.util.Locale\",\"hooked_method\":\"readObject\",\"type\":\"reflection\",\"class\":\"java.lang.reflect.Method\",\"timestamp\":1508566163726},{\"args\":[\"android.os.Parcel$2@ba14378\"],\"method\":\"invoke\",\"hooked_class\":\"java.util.Locale\",\"hooked_method\":\"readObject\",\"type\":\"reflection\",\"class\":\"java.lang.reflect.Method\",\"timestamp\":1508566163790},{\"args\":[\"android.os.Parcel$2@1631f24\"],\"method\":\"invoke\",\"hooked_class\":\"java.util.Locale\",\"hooked_method\":\"readObject\",\"type\":\"reflection\",\"class\":\"java.lang.reflect.Method\",\"timestamp\":1508566163792},{\"args\":[\"android.os.Parcel$2@a3f90f4\"],\"method\":\"invoke\",\"hooked_class\":\"java.util.Locale\",\"hooked_method\":\"readObject\",\"type\":\"reflection\",\"class\":\"java.lang.reflect.Method\",\"timestamp\":1508566163781},{\"args\":[\"android.os.Parcel$2@562a197\"],\"method\":\"invoke\",\"hooked_class\":\"java.util.Locale\",\"hooked_method\":\"readObject\",\"type\":\"reflection\",\"class\":\"java.lang.reflect.Method\",\"timestamp\":1508566163830},{\"args\":[\"android.os.Parcel$2@941d010\"],\"method\":\"invoke\",\"hooked_class\":\"java.util.Locale\",\"hooked_method\":\"readObject\",\"type\":\"reflection\",\"class\":\"java.lang.reflect.Method\",\"timestamp\":1508566163706},{\"args\":[\"android.os.Parcel$2@f28032f\"],\"method\":\"invoke\",\"hooked_class\":\"java.util.Locale\",\"hooked_method\":\"readObject\",\"type\":\"reflection\",\"class\":\"java.lang.reflect.Method\",\"timestamp\":1508566163708},{\"args\":[\"android.os.Parcel$2@508c119\"],\"method\":\"invoke\",\"hooked_class\":\"java.util.Locale\",\"hooked_method\":\"readObject\",\"type\":\"reflection\",\"class\":\"java.lang.reflect.Method\",\"timestamp\":1508566163785},{\"args\":[\"gsm.operator.iso-country\"],\"result\":\"\",\"method\":\"get\",\"type\":\"content\",\"class\":\"android.os.SystemProperties\",\"timestamp\":1508566162728},{\"args\":[\"android.os.Parcel$2@97ed4ac\"],\"method\":\"invoke\",\"hooked_class\":\"java.util.Locale\",\"hooked_method\":\"readObject\",\"type\":\"reflection\",\"class\":\"java.lang.reflect.Method\",\"timestamp\":1508566163660},{\"args\":[\"android.os.Parcel$2@93e6d26\"],\"method\":\"invoke\",\"hooked_class\":\"java.util.Locale\",\"hooked_method\":\"readObject\",\"type\":\"reflection\",\"class\":\"java.lang.reflect.Method\",\"timestamp\":1508566163651},{\"args\":[\"android.os.Parcel$2@d86f2b6\"],\"method\":\"invoke\",\"hooked_class\":\"java.util.Locale\",\"hooked_method\":\"readObject\",\"type\":\"reflection\",\"class\":\"java.lang.reflect.Method\",\"timestamp\":1508566163791},{\"args\":[\"android.os.Parcel$2@3310c15\"],\"method\":\"invoke\",\"hooked_class\":\"java.util.Locale\",\"hooked_method\":\"readObject\",\"type\":\"reflection\",\"class\":\"java.lang.reflect.Method\",\"timestamp\":1508566163742},{\"args\":[\"android.os.Parcel$2@79a38f5\"],\"method\":\"invoke\",\"hooked_class\":\"java.util.Locale\",\"hooked_method\":\"readObject\",\"type\":\"reflection\",\"class\":\"java.lang.reflect.Method\",\"timestamp\":1508566163765},{\"args\":[\"android.os.Parcel$2@acebb2a\"],\"method\":\"invoke\",\"hooked_class\":\"java.util.Locale\",\"hooked_method\":\"readObject\",\"type\":\"reflection\",\"class\":\"java.lang.reflect.Method\",\"timestamp\":1508566163743},{\"args\":[\"android.os.Parcel$2@c67cf35\"],\"method\":\"invoke\",\"hooked_class\":\"java.util.Locale\",\"hooked_method\":\"readObject\",\"type\":\"reflection\",\"class\":\"java.lang.reflect.Method\",\"timestamp\":1508566163720},{\"args\":[\"android.os.Parcel$2@b4ac437\"],\"method\":\"invoke\",\"hooked_class\":\"java.util.Locale\",\"hooked_method\":\"readObject\",\"type\":\"reflection\",\"class\":\"java.lang.reflect.Method\",\"timestamp\":1508566163702},{\"args\":[\"chbTouchBtn\",\"false\"],\"result\":{\"mClear\":false,\"mModified\":{\"chbTouchBtn\":false}},\"method\":\"putBoolean\",\"type\":\"globals\",\"class\":\"android.app.SharedPreferencesImpl$EditorImpl\",\"timestamp\":1508566191940},{\"args\":[\"/data/data/com.devadvance.rootcloak2/shared_prefs/CustomizeApps.xml\",\"0\"],\"result\":{\"descriptor\":15},\"method\":\"open\",\"type\":\"file\",\"class\":\"libcore.io.IoBridge\",\"timestamp\":1508566162314},{\"args\":[\"android.os.Parcel$2@df042cb\"],\"method\":\"invoke\",\"hooked_class\":\"java.util.Locale\",\"hooked_method\":\"readObject\",\"type\":\"reflection\",\"class\":\"java.lang.reflect.Method\",\"timestamp\":1508566163806},{\"args\":[\"android.os.Parcel$2@1a8c90a\"],\"method\":\"invoke\",\"hooked_class\":\"java.util.Locale\",\"hooked_method\":\"readObject\",\"type\":\"reflection\",\"class\":\"java.lang.reflect.Method\",\"timestamp\":1508566163662},{\"args\":[\"android.os.Parcel$2@58d88ba\"],\"method\":\"invoke\",\"hooked_class\":\"java.util.Locale\",\"hooked_method\":\"readObject\",\"type\":\"reflection\",\"class\":\"java.lang.reflect.Method\",\"timestamp\":1508566163688},{\"args\":[{\"mDebugUnregister\":false},{\"mHasPartialTypes\":false,\"mPriority\":0,\"mActions\":[\"android.intent.action.APPLICATION_RESTRICTIONS_CHANGED\"],\"mVerifyState\":0},\"Handler (android.os.Handler) {42b2e1b}\"],\"method\":\"registerReceiver\",\"type\":\"binder\",\"class\":\"android.app.ContextImpl\",\"timestamp\":1508566162435},{\"args\":[\"debug.second-display.pkg\"],\"result\":\"\",\"method\":\"get\",\"type\":\"content\",\"class\":\"android.os.SystemProperties\",\"timestamp\":1508566191890},{\"args\":[\"/data/app/com.google.android.webview-1/base.apk\"],\"method\":\"dalvik.system.DexFile\",\"type\":\"dex\",\"class\":\"dalvik.system.DexFile\",\"timestamp\":1508566162305},{\"args\":[\"android.os.Parcel$2@ce66e64\"],\"method\":\"invoke\",\"hooked_class\":\"java.util.Locale\",\"hooked_method\":\"readObject\",\"type\":\"reflection\",\"class\":\"java.lang.reflect.Method\",\"timestamp\":1508566163747},{\"args\":[\"android.os.Parcel$2@8835918\"],\"method\":\"invoke\",\"hooked_class\":\"java.util.Locale\",\"hooked_method\":\"readObject\",\"type\":\"reflection\",\"class\":\"java.lang.reflect.Method\",\"timestamp\":1508566163767},{\"args\":[\"android.os.Parcel$2@ea1f38b\"],\"method\":\"invoke\",\"hooked_class\":\"java.util.Locale\",\"hooked_method\":\"readObject\",\"type\":\"reflection\",\"class\":\"java.lang.reflect.Method\",\"timestamp\":1508566163648},{\"args\":[],\"result\":\"\",\"method\":\"getNetworkCountryIso\",\"type\":\"fingerprint\",\"class\":\"android.telephony.TelephonyManager\",\"timestamp\":1508566162674},{\"args\":[\"android.os.Parcel$2@466a5e8\"],\"method\":\"invoke\",\"hooked_class\":\"java.util.Locale\",\"hooked_method\":\"readObject\",\"type\":\"reflection\",\"class\":\"java.lang.reflect.Method\",\"timestamp\":1508566163755},{\"args\":[\"android.os.Parcel$2@dab1fae\"],\"method\":\"invoke\",\"hooked_class\":\"java.util.Locale\",\"hooked_method\":\"readObject\",\"type\":\"reflection\",\"class\":\"java.lang.reflect.Method\",\"timestamp\":1508566163685},{\"args\":[\"android.os.Parcel$2@69ff53b\"],\"method\":\"invoke\",\"hooked_class\":\"java.util.Locale\",\"hooked_method\":\"readObject\",\"type\":\"reflection\",\"class\":\"java.lang.reflect.Method\",\"timestamp\":1508566163722},{\"args\":[\"android.os.Parcel$2@88b3848\"],\"method\":\"invoke\",\"hooked_class\":\"java.util.Locale\",\"hooked_method\":\"readObject\",\"type\":\"reflection\",\"class\":\"java.lang.reflect.Method\",\"timestamp\":1508566163779}"}