{"pkg_name": "com.wsl.calorific", "api_calls": "{\"args\":[\"ro.config.low_ram\",\"false\"],\"result\":\"false\",\"method\":\"get\",\"type\":\"content\",\"class\":\"android.os.SystemProperties\",\"timestamp\":1507987380388},{\"args\":[\"ro.config.low_ram\",\"false\"],\"result\":\"false\",\"method\":\"get\",\"type\":\"content\",\"class\":\"android.os.SystemProperties\",\"timestamp\":1507987345142},{\"args\":[\"ro.config.low_ram\",\"false\"],\"result\":\"false\",\"method\":\"get\",\"type\":\"content\",\"class\":\"android.os.SystemProperties\",\"timestamp\":1507987324285},{\"args\":[\"ro.config.low_ram\",\"false\"],\"result\":\"false\",\"method\":\"get\",\"type\":\"content\",\"class\":\"android.os.SystemProperties\",\"timestamp\":1507987324593},{\"args\":[{\"path\":{\"decoded\":\"NOT CACHED\",\"encoded\":\"/secure/accessibility_captioning_typeface\"},\"fragment\":{},\"scheme\":\"content\",\"port\":-2,\"authority\":{\"decoded\":\"settings\",\"encoded\":\"NOT CACHED\"},\"query\":{},\"uriString\":\"NOT CACHED\",\"host\":\"NOT CACHED\"},\"false\",\"android.view.accessibility.CaptioningManager$MyContentObserver@e83e2c5\",\"0\"],\"method\":\"registerContentObserver\",\"type\":\"content\",\"class\":\"android.content.ContentResolver\",\"timestamp\":1507987389269},{\"args\":[\"ro.config.low_ram\",\"false\"],\"result\":\"false\",\"method\":\"get\",\"type\":\"content\",\"class\":\"android.os.SystemProperties\",\"timestamp\":1507987423406},{\"args\":[\"ro.config.low_ram\",\"false\"],\"result\":\"false\",\"method\":\"get\",\"type\":\"content\",\"class\":\"android.os.SystemProperties\",\"timestamp\":1507987324119},{\"args\":[\"/data/user/0/com.wsl.calorific/shared_prefs/CalorificSettings.xml\",\"577\"],\"result\":{\"descriptor\":21},\"method\":\"open\",\"type\":\"file\",\"class\":\"libcore.io.IoBridge\",\"timestamp\":1507987324540},{\"args\":[\"ro.config.low_ram\",\"false\"],\"result\":\"false\",\"method\":\"get\",\"type\":\"content\",\"class\":\"android.os.SystemProperties\",\"timestamp\":1507987324118},{\"args\":[{\"path\":{\"decoded\":\"NOT CACHED\",\"encoded\":\"/secure/accessibility_captioning_edge_type\"},\"fragment\":{},\"scheme\":\"content\",\"port\":-2,\"authority\":{\"decoded\":\"settings\",\"encoded\":\"settings\"},\"query\":{},\"uriString\":\"NOT CACHED\",\"host\":\"NOT CACHED\"},\"false\",\"android.view.accessibility.CaptioningManager$MyContentObserver@e83e2c5\"],\"method\":\"registerContentObserver\",\"type\":\"content\",\"class\":\"android.content.ContentResolver\",\"timestamp\":1507987389218},{\"args\":[\"ro.config.low_ram\",\"false\"],\"result\":\"false\",\"method\":\"get\",\"type\":\"content\",\"class\":\"android.os.SystemProperties\",\"timestamp\":1507987423405},{\"args\":[{\"act\":\"android.intent.action.MAIN\",\"cmp\":\"com.wsl.calorific/com.wsl.calorific.dashboard.DashboardActivity\"}],\"method\":\"startActivity\",\"type\":\"binder\",\"class\":\"android.app.Activity\",\"timestamp\":1507987432325},{\"args\":[{\"path\":{\"decoded\":\"NOT CACHED\",\"encoded\":\"/secure/accessibility_captioning_edge_color\"},\"fragment\":{},\"scheme\":\"content\",\"port\":-2,\"authority\":{\"decoded\":\"settings\",\"encoded\":\"settings\"},\"query\":{},\"uriString\":\"NOT CACHED\",\"host\":\"NOT CACHED\"},\"false\",\"android.view.accessibility.CaptioningManager$MyContentObserver@e83e2c5\"],\"method\":\"registerContentObserver\",\"type\":\"content\",\"class\":\"android.content.ContentResolver\",\"timestamp\":1507987389252},{\"args\":[{\"path\":{\"decoded\":\"NOT CACHED\",\"encoded\":\"/secure/accessibility_captioning_enabled\"},\"fragment\":{},\"scheme\":\"content\",\"port\":-2,\"authority\":{\"decoded\":\"settings\",\"encoded\":\"NOT CACHED\"},\"query\":{},\"uriString\":\"NOT CACHED\",\"host\":\"NOT CACHED\"},\"false\",\"android.view.accessibility.CaptioningManager$MyContentObserver@e83e2c5\",\"0\"],\"method\":\"registerContentObserver\",\"type\":\"content\",\"class\":\"android.content.ContentResolver\",\"timestamp\":1507987389066},{\"args\":[{\"path\":{\"decoded\":\"NOT CACHED\",\"encoded\":\"/secure/accessibility_captioning_window_color\"},\"fragment\":{},\"scheme\":\"content\",\"port\":-2,\"authority\":{\"decoded\":\"settings\",\"encoded\":\"settings\"},\"query\":{},\"uriString\":\"NOT CACHED\",\"host\":\"NOT CACHED\"},\"false\",\"android.view.accessibility.CaptioningManager$MyContentObserver@e83e2c5\"],\"method\":\"registerContentObserver\",\"type\":\"content\",\"class\":\"android.content.ContentResolver\",\"timestamp\":1507987389184},{\"args\":[\"ro.config.low_ram\",\"false\"],\"result\":\"false\",\"method\":\"get\",\"type\":\"content\",\"class\":\"android.os.SystemProperties\",\"timestamp\":1507987345143},{\"args\":[\"key_replication_generation\",\"2\"],\"result\":{\"mClear\":false,\"mModified\":{\"key_replication_generation\":2}},\"method\":\"putInt\",\"type\":\"globals\",\"class\":\"android.app.SharedPreferencesImpl$EditorImpl\",\"timestamp\":1507987458121},{\"args\":[\"debug.second-display.pkg\"],\"result\":\"\",\"method\":\"get\",\"type\":\"content\",\"class\":\"android.os.SystemProperties\",\"timestamp\":1507987354420},{\"args\":[\"ro.config.low_ram\",\"false\"],\"result\":\"false\",\"method\":\"get\",\"type\":\"content\",\"class\":\"android.os.SystemProperties\",\"timestamp\":1507987354427},{\"args\":[\"ro.config.low_ram\",\"false\"],\"result\":\"false\",\"method\":\"get\",\"type\":\"content\",\"class\":\"android.os.SystemProperties\",\"timestamp\":1507987389034},{\"args\":[\"ro.config.low_ram\",\"false\"],\"result\":\"false\",\"method\":\"get\",\"type\":\"content\",\"class\":\"android.os.SystemProperties\",\"timestamp\":1507987337140},{\"args\":[\"KEY_WARNING_SHOWN_SINCE_ON_EXTERNAL_STORAGE\",\"false\"],\"result\":{\"mClear\":false,\"mModified\":{\"KEY_WARNING_SHOWN_SINCE_ON_EXTERNAL_STORAGE\":false}},\"method\":\"putBoolean\",\"type\":\"globals\",\"class\":\"android.app.SharedPreferencesImpl$EditorImpl\",\"timestamp\":1507987324098},{\"args\":[\"persist.sys.timezone\"],\"result\":\"America/New_York\",\"method\":\"get\",\"type\":\"content\",\"class\":\"android.os.SystemProperties\",\"timestamp\":1507987380364},{\"args\":[{\"mDebugUnregister\":false},{\"mHasPartialTypes\":false,\"mPriority\":0,\"mActions\":[\"android.intent.action.APPLICATION_RESTRICTIONS_CHANGED\"],\"mVerifyState\":0},\"Handler (android.os.Handler) {ce2d5a}\"],\"method\":\"registerReceiver\",\"type\":\"binder\",\"class\":\"android.app.ContextImpl\",\"timestamp\":1507987388789},{\"args\":[\"key_first_application_start_time\",\"1507987324528\"],\"result\":{\"mClear\":false,\"mModified\":{\"key_first_application_start_time\":1507987324528}},\"method\":\"putLong\",\"type\":\"globals\",\"class\":\"android.app.SharedPreferencesImpl$EditorImpl\",\"timestamp\":1507987324528},{\"args\":[\"debug.second-display.pkg\"],\"result\":\"\",\"method\":\"get\",\"type\":\"content\",\"class\":\"android.os.SystemProperties\",\"timestamp\":1507987345139},{\"args\":[\"ro.config.low_ram\",\"false\"],\"result\":\"false\",\"method\":\"get\",\"type\":\"content\",\"class\":\"android.os.SystemProperties\",\"timestamp\":1507987389035},{\"args\":[\"ro.config.low_ram\",\"false\"],\"result\":\"false\",\"method\":\"get\",\"type\":\"content\",\"class\":\"android.os.SystemProperties\",\"timestamp\":1507987324557},{\"args\":[\"debug.sqlite.journalmode\",\"PERSIST\"],\"result\":\"PERSIST\",\"method\":\"get\",\"type\":\"content\",\"class\":\"android.os.SystemProperties\",\"timestamp\":1507987354513},{\"args\":[\"debug.second-display.pkg\"],\"result\":\"\",\"method\":\"get\",\"type\":\"content\",\"class\":\"android.os.SystemProperties\",\"timestamp\":1507987423397},{\"args\":[\"ro.config.low_ram\",\"false\"],\"result\":\"false\",\"method\":\"get\",\"type\":\"content\",\"class\":\"android.os.SystemProperties\",\"timestamp\":1507987354426},{\"args\":[\"ro.config.low_ram\",\"false\"],\"result\":\"false\",\"method\":\"get\",\"type\":\"content\",\"class\":\"android.os.SystemProperties\",\"timestamp\":1507987324117},{\"args\":[{\"path\":{\"decoded\":\"NOT CACHED\",\"encoded\":\"/secure/accessibility_captioning_font_scale\"},\"fragment\":{},\"scheme\":\"content\",\"port\":-2,\"authority\":{\"decoded\":\"settings\",\"encoded\":\"NOT CACHED\"},\"query\":{},\"uriString\":\"NOT CACHED\",\"host\":\"NOT CACHED\"},\"false\",\"android.view.accessibility.CaptioningManager$MyContentObserver@e83e2c5\",\"0\"],\"method\":\"registerContentObserver\",\"type\":\"content\",\"class\":\"android.content.ContentResolver\",\"timestamp\":1507987389302},{\"args\":[{\"path\":{\"decoded\":\"NOT CACHED\",\"encoded\":\"/secure/accessibility_captioning_background_color\"},\"fragment\":{},\"scheme\":\"content\",\"port\":-2,\"authority\":{\"decoded\":\"settings\",\"encoded\":\"NOT CACHED\"},\"query\":{},\"uriString\":\"NOT CACHED\",\"host\":\"NOT CACHED\"},\"false\",\"android.view.accessibility.CaptioningManager$MyContentObserver@e83e2c5\",\"0\"],\"method\":\"registerContentObserver\",\"type\":\"content\",\"class\":\"android.content.ContentResolver\",\"timestamp\":1507987389135},{\"args\":[{\"path\":{\"decoded\":\"NOT CACHED\",\"encoded\":\"/secure/accessibility_captioning_edge_color\"},\"fragment\":{},\"scheme\":\"content\",\"port\":-2,\"authority\":{\"decoded\":\"settings\",\"encoded\":\"NOT CACHED\"},\"query\":{},\"uriString\":\"NOT CACHED\",\"host\":\"NOT CACHED\"},\"false\",\"android.view.accessibility.CaptioningManager$MyContentObserver@e83e2c5\",\"0\"],\"method\":\"registerContentObserver\",\"type\":\"content\",\"class\":\"android.content.ContentResolver\",\"timestamp\":1507987389234},{\"args\":[\"access_code_signature\",\"a476caadad0d57ab05e6ed3589e4bc5eaa60db98\"],\"result\":{\"mClear\":false,\"mModified\":{\"access_code_signature\":\"a476caadad0d57ab05e6ed3589e4bc5eaa60db98\",\"web_access_code\":\"4UI5DBT8\"}},\"method\":\"putString\",\"type\":\"globals\",\"class\":\"android.app.SharedPreferencesImpl$EditorImpl\",\"timestamp\":1507987414846},{\"args\":[\"ro.config.low_ram\",\"false\"],\"result\":\"false\",\"method\":\"get\",\"type\":\"content\",\"class\":\"android.os.SystemProperties\",\"timestamp\":1507987324279},{\"args\":[\"debug.second-display.pkg\"],\"result\":\"\",\"method\":\"get\",\"type\":\"content\",\"class\":\"android.os.SystemProperties\",\"timestamp\":1507987336451},{\"args\":[\"/data/user/0/com.wsl.calorific/files/.flurryagent.743d2480\",\"577\"],\"result\":{\"descriptor\":19},\"method\":\"open\",\"type\":\"file\",\"class\":\"libcore.io.IoBridge\",\"timestamp\":1507987379951},{\"args\":[\"org.chromium.android_webview.ResourcesContextWrapperFactory$WebViewContextWrapper@f26b567\",{}],\"method\":\"invoke\",\"hooked_class\":\"\",\"hooked_method\":\"getUserOptInPreference\",\"type\":\"reflection\",\"class\":\"java.lang.reflect.Method\",\"timestamp\":1507987388863},{\"args\":[\"ro.config.low_ram\",\"false\"],\"result\":\"false\",\"method\":\"get\",\"type\":\"content\",\"class\":\"android.os.SystemProperties\",\"timestamp\":1507987432343},{\"args\":[\"ro.config.low_ram\",\"false\"],\"result\":\"false\",\"method\":\"get\",\"type\":\"content\",\"class\":\"android.os.SystemProperties\",\"timestamp\":1507987423407},{\"args\":[\"ro.config.low_ram\",\"false\"],\"result\":\"false\",\"method\":\"get\",\"type\":\"content\",\"class\":\"android.os.SystemProperties\",\"timestamp\":1507987441118},{\"args\":[\"/data/user/0/com.wsl.calorific/shared_prefs/CalorificSettings.xml\",\"577\"],\"result\":{\"descriptor\":47},\"method\":\"open\",\"type\":\"file\",\"class\":\"libcore.io.IoBridge\",\"timestamp\":1507987397372},{\"args\":[{\"mDebugUnregister\":false},{\"mHasPartialTypes\":false,\"mPriority\":0,\"mActions\":[\"android.intent.action.PROXY_CHANGE\"],\"mVerifyState\":0}],\"method\":\"registerReceiver\",\"type\":\"binder\",\"class\":\"android.app.ContextImpl\",\"timestamp\":1507987388950},{\"args\":[\"/data/user/0/com.wsl.calorific/files/.flurryagent.743d2480\",\"577\"],\"result\":{\"descriptor\":19},\"method\":\"open\",\"type\":\"file\",\"class\":\"libcore.io.IoBridge\",\"timestamp\":1507987388576},{\"args\":[\"key_main_dashboard_button_clicked\",\"true\"],\"result\":{\"mClear\":false,\"mModified\":{\"key_main_dashboard_button_clicked\":true}},\"method\":\"putBoolean\",\"type\":\"globals\",\"class\":\"android.app.SharedPreferencesImpl$EditorImpl\",\"timestamp\":1507987414758},{\"args\":[\"/data/user/0/com.wsl.calorific/shared_prefs/CalorificSettings.xml\",\"577\"],\"result\":{\"descriptor\":70},\"method\":\"open\",\"type\":\"file\",\"class\":\"libcore.io.IoBridge\",\"timestamp\":1507987458124},{\"args\":[\"key_calorific_wakeup_hour\",\"8\"],\"result\":{\"mClear\":false,\"mModified\":{\"key_calorific_wakeup_hour\":8}},\"method\":\"putInt\",\"type\":\"globals\",\"class\":\"android.app.SharedPreferencesImpl$EditorImpl\",\"timestamp\":1507987397405},{\"args\":[\"ro.config.low_ram\",\"false\"],\"result\":\"false\",\"method\":\"get\",\"type\":\"content\",\"class\":\"android.os.SystemProperties\",\"timestamp\":1507987362601},{\"args\":[\"/data/user/0/com.wsl.calorific/files/.flurryagent.743d2480\",\"0\"],\"result\":{\"descriptor\":18},\"method\":\"open\",\"type\":\"file\",\"class\":\"libcore.io.IoBridge\",\"timestamp\":1507987380354},{\"args\":[\"ro.config.low_ram\",\"false\"],\"result\":\"false\",\"method\":\"get\",\"type\":\"content\",\"class\":\"android.os.SystemProperties\",\"timestamp\":1507987336457},{\"args\":[],\"result\":[\"GREEN\",\"YELLOW\",\"RED\",\"WATER\"],\"method\":\"invoke\",\"hooked_class\":\"\",\"hooked_method\":\"values\",\"type\":\"reflection\",\"class\":\"java.lang.reflect.Method\",\"timestamp\":1507987336481},{\"args\":[\"/data/user/0/com.wsl.calorific/shared_prefs/CalorificSettings.xml\",\"577\"],\"result\":{\"descriptor\":47},\"method\":\"open\",\"type\":\"file\",\"class\":\"libcore.io.IoBridge\",\"timestamp\":1507987397407},{\"args\":[\"debug.second-display.pkg\"],\"result\":\"\",\"method\":\"get\",\"type\":\"content\",\"class\":\"android.os.SystemProperties\",\"timestamp\":1507987441065},{\"args\":[\"ro.config.low_ram\",\"false\"],\"result\":\"false\",\"method\":\"get\",\"type\":\"content\",\"class\":\"android.os.SystemProperties\",\"timestamp\":1507987441116},{\"args\":[{\"path\":{\"decoded\":\"NOT CACHED\",\"encoded\":\"/secure/accessibility_captioning_edge_type\"},\"fragment\":{},\"scheme\":\"content\",\"port\":-2,\"authority\":{\"decoded\":\"settings\",\"encoded\":\"NOT CACHED\"},\"query\":{},\"uriString\":\"NOT CACHED\",\"host\":\"NOT CACHED\"},\"false\",\"android.view.accessibility.CaptioningManager$MyContentObserver@e83e2c5\",\"0\"],\"method\":\"registerContentObserver\",\"type\":\"content\",\"class\":\"android.content.ContentResolver\",\"timestamp\":1507987389201},{\"args\":[\"ro.config.low_ram\",\"false\"],\"result\":\"false\",\"method\":\"get\",\"type\":\"content\",\"class\":\"android.os.SystemProperties\",\"timestamp\":1507987432387},{\"args\":[\"ro.config.low_ram\",\"false\"],\"result\":\"false\",\"method\":\"get\",\"type\":\"content\",\"class\":\"android.os.SystemProperties\",\"timestamp\":1507987362600},{\"args\":[\"debug.second-display.pkg\"],\"result\":\"\",\"method\":\"get\",\"type\":\"content\",\"class\":\"android.os.SystemProperties\",\"timestamp\":1507987371259},{\"args\":[\"ro.config.low_ram\",\"false\"],\"result\":\"false\",\"method\":\"get\",\"type\":\"content\",\"class\":\"android.os.SystemProperties\",\"timestamp\":1507987406051},{\"args\":[\"debug.second-display.pkg\"],\"result\":\"\",\"method\":\"get\",\"type\":\"content\",\"class\":\"android.os.SystemProperties\",\"timestamp\":1507987414717},{\"args\":[\"debug.second-display.pkg\"],\"result\":\"\",\"method\":\"get\",\"type\":\"content\",\"class\":\"android.os.SystemProperties\",\"timestamp\":1507987324111},{\"args\":[\"debug.sqlite.syncmode\",\"FULL\"],\"result\":\"FULL\",\"method\":\"get\",\"type\":\"content\",\"class\":\"android.os.SystemProperties\",\"timestamp\":1507987324198},{\"args\":[\"/data/user/0/com.wsl.calorific/shared_prefs/GlobalPreference.xml\",\"577\"],\"result\":{\"descriptor\":60},\"method\":\"open\",\"type\":\"file\",\"class\":\"libcore.io.IoBridge\",\"timestamp\":1507987414848},{\"args\":[\"ro.config.low_ram\",\"false\"],\"result\":\"false\",\"method\":\"get\",\"type\":\"content\",\"class\":\"android.os.SystemProperties\",\"timestamp\":1507987345146},{\"args\":[\"ro.config.low_ram\",\"false\"],\"result\":\"false\",\"method\":\"get\",\"type\":\"content\",\"class\":\"android.os.SystemProperties\",\"timestamp\":1507987362603},{\"args\":[{\"path\":{\"decoded\":\"NOT CACHED\",\"encoded\":\"/secure/accessibility_captioning_foreground_color\"},\"fragment\":{},\"scheme\":\"content\",\"port\":-2,\"authority\":{\"decoded\":\"settings\",\"encoded\":\"settings\"},\"query\":{},\"uriString\":\"NOT CACHED\",\"host\":\"NOT CACHED\"},\"false\",\"android.view.accessibility.CaptioningManager$MyContentObserver@e83e2c5\"],\"method\":\"registerContentObserver\",\"type\":\"content\",\"class\":\"android.content.ContentResolver\",\"timestamp\":1507987389119},{\"args\":[{\"path\":{\"decoded\":\"NOT CACHED\",\"encoded\":\"/secure/accessibility_captioning_locale\"},\"fragment\":{},\"scheme\":\"content\",\"port\":-2,\"authority\":{\"decoded\":\"settings\",\"encoded\":\"NOT CACHED\"},\"query\":{},\"uriString\":\"NOT CACHED\",\"host\":\"NOT CACHED\"},\"false\",\"android.view.accessibility.CaptioningManager$MyContentObserver@e83e2c5\",\"0\"],\"method\":\"registerContentObserver\",\"type\":\"content\",\"class\":\"android.content.ContentResolver\",\"timestamp\":1507987389335},{\"args\":[\"ro.config.low_ram\",\"false\"],\"result\":\"false\",\"method\":\"get\",\"type\":\"content\",\"class\":\"android.os.SystemProperties\",\"timestamp\":1507987423475},{\"args\":[{\"path\":{\"decoded\":\"NOT CACHED\",\"encoded\":\"/secure/accessibility_captioning_locale\"},\"fragment\":{},\"scheme\":\"content\",\"port\":-2,\"authority\":{\"decoded\":\"settings\",\"encoded\":\"settings\"},\"query\":{},\"uriString\":\"NOT CACHED\",\"host\":\"NOT CACHED\"},\"false\",\"android.view.accessibility.CaptioningManager$MyContentObserver@e83e2c5\"],\"method\":\"registerContentObserver\",\"type\":\"content\",\"class\":\"android.content.ContentResolver\",\"timestamp\":1507987389352},{\"args\":[\"ro.config.low_ram\",\"false\"],\"result\":\"false\",\"method\":\"get\",\"type\":\"content\",\"class\":\"android.os.SystemProperties\",\"timestamp\":1507987441115},{\"args\":[\"webviewchromium\"],\"result\":\"/data/app/com.google.android.webview-1/lib/arm/libwebviewchromium.so\",\"method\":\"findLibrary\",\"type\":\"dex\",\"class\":\"dalvik.system.BaseDexClassLoader\",\"timestamp\":1507987388730},{\"args\":[{\"cachedSsi\":7,\"scheme\":\"content\",\"port\":-2,\"authority\":{\"decoded\":\"com.wsl.CardioTrainer.exerciseinfo\",\"encoded\":\"com.wsl.CardioTrainer.exerciseinfo\"},\"uriString\":\"content://com.wsl.CardioTrainer.exerciseinfo\",\"host\":\"NOT CACHED\",\"cachedFsi\":-2},[\"accessCode\"]],\"method\":\"query\",\"type\":\"content\",\"class\":\"android.content.ContentResolver\",\"timestamp\":1507987414834},{\"args\":[\"ro.config.low_ram\",\"false\"],\"result\":\"false\",\"method\":\"get\",\"type\":\"content\",\"class\":\"android.os.SystemProperties\",\"timestamp\":1507987324276},{\"args\":[\"ro.config.low_ram\",\"false\"],\"result\":\"false\",\"method\":\"get\",\"type\":\"content\",\"class\":\"android.os.SystemProperties\",\"timestamp\":1507987441150},{\"args\":[\"ro.config.low_ram\",\"false\"],\"result\":\"false\",\"method\":\"get\",\"type\":\"content\",\"class\":\"android.os.SystemProperties\",\"timestamp\":1507987441114},{\"args\":[\"ro.config.low_ram\",\"false\"],\"result\":\"false\",\"method\":\"get\",\"type\":\"content\",\"class\":\"android.os.SystemProperties\",\"timestamp\":1507987389033},{\"args\":[\"lastVersionCodeUsed\",\"316309800\"],\"result\":{\"mClear\":false,\"mModified\":{\"lastVersionCodeUsed\":316309800}},\"method\":\"putInt\",\"type\":\"globals\",\"class\":\"android.app.SharedPreferencesImpl$EditorImpl\",\"timestamp\":1507987388754},{\"args\":[\"ro.config.low_ram\",\"false\"],\"result\":\"false\",\"method\":\"get\",\"type\":\"content\",\"class\":\"android.os.SystemProperties\",\"timestamp\":1507987336455},{\"args\":[\"debug.second-display.pkg\"],\"result\":\"\",\"method\":\"get\",\"type\":\"content\",\"class\":\"android.os.SystemProperties\",\"timestamp\":1507987432333},{\"args\":[\"ro.config.low_ram\",\"false\"],\"result\":\"false\",\"method\":\"get\",\"type\":\"content\",\"class\":\"android.os.SystemProperties\",\"timestamp\":1507987345163},{\"args\":[\"/data/user/0/com.wsl.calorific/shared_prefs/CalorificSettings.xml\",\"0\"],\"result\":{\"descriptor\":15},\"method\":\"open\",\"type\":\"file\",\"class\":\"libcore.io.IoBridge\",\"timestamp\":1507987380250},{\"args\":[\"/data/data/com.devadvance.rootcloak2/shared_prefs/CustomizeCommands.xml\",\"0\"],\"result\":{\"descriptor\":23},\"method\":\"open\",\"type\":\"file\",\"class\":\"libcore.io.IoBridge\",\"timestamp\":1507987388677},{\"args\":[\"ro.config.low_ram\",\"false\"],\"result\":\"false\",\"method\":\"get\",\"type\":\"content\",\"class\":\"android.os.SystemProperties\",\"timestamp\":1507987354425},{\"args\":[\"ro.config.low_ram\",\"false\"],\"result\":\"false\",\"method\":\"get\",\"type\":\"content\",\"class\":\"android.os.SystemProperties\",\"timestamp\":1507987336453},{\"args\":[\"persist.sys.timezone\"],\"result\":\"America/New_York\",\"method\":\"get\",\"type\":\"content\",\"class\":\"android.os.SystemProperties\",\"timestamp\":1507987354507},{\"args\":[{\"cachedSsi\":7,\"scheme\":\"content\",\"port\":-2,\"authority\":{\"decoded\":\"com.wsl.CardioTrainer.exerciseinfo\",\"encoded\":\"com.wsl.CardioTrainer.exerciseinfo\"},\"uriString\":\"content://com.wsl.CardioTrainer.exerciseinfo\",\"host\":\"NOT CACHED\",\"cachedFsi\":-2},[\"accessCode\"]],\"method\":\"query\",\"type\":\"content\",\"class\":\"android.content.ContentResolver\",\"timestamp\":1507987414828},{\"args\":[\"ro.config.low_ram\",\"false\"],\"result\":\"false\",\"method\":\"get\",\"type\":\"content\",\"class\":\"android.os.SystemProperties\",\"timestamp\":1507987362599},{\"args\":[\"/data/app/com.google.android.webview-1/base.apk\",\"0\"],\"result\":{\"descriptor\":21},\"method\":\"open\",\"type\":\"file\",\"class\":\"libcore.io.IoBridge\",\"timestamp\":1507987388733},{\"args\":[\"/data/user/0/com.wsl.calorific/files/.flurryagent.743d2480\",\"577\"],\"result\":{\"descriptor\":47},\"method\":\"open\",\"type\":\"file\",\"class\":\"libcore.io.IoBridge\",\"timestamp\":1507987406041},{\"args\":[\"ro.config.low_ram\",\"false\"],\"result\":\"false\",\"method\":\"get\",\"type\":\"content\",\"class\":\"android.os.SystemProperties\",\"timestamp\":1507987345144},{\"args\":[],\"result\":[\"SANS_SERIF\",\"SERIF\",\"MONOSPACE\"],\"method\":\"invoke\",\"hooked_class\":\"\",\"hooked_method\":\"values\",\"type\":\"reflection\",\"class\":\"java.lang.reflect.Method\",\"timestamp\":1507987389409},{\"args\":[\"ro.config.low_ram\",\"false\"],\"result\":\"false\",\"method\":\"get\",\"type\":\"content\",\"class\":\"android.os.SystemProperties\",\"timestamp\":1507987336454},{\"args\":[\"key_use_metric_units\",\"false\"],\"result\":{\"mClear\":false,\"mModified\":{\"key_use_metric_units\":false}},\"method\":\"putBoolean\",\"type\":\"globals\",\"class\":\"android.app.SharedPreferencesImpl$EditorImpl\",\"timestamp\":1507987397370},{\"args\":[\"ro.config.low_ram\",\"false\"],\"result\":\"false\",\"method\":\"get\",\"type\":\"content\",\"class\":\"android.os.SystemProperties\",\"timestamp\":1507987354476},{\"args\":[\"/data/user/0/com.wsl.calorific/files/.flurryagent.743d2480\",\"577\"],\"result\":{\"descriptor\":21},\"method\":\"open\",\"type\":\"file\",\"class\":\"libcore.io.IoBridge\",\"timestamp\":1507987336447},{\"args\":[\"ro.config.low_ram\",\"false\"],\"result\":\"false\",\"method\":\"get\",\"type\":\"content\",\"class\":\"android.os.SystemProperties\",\"timestamp\":1507987397332},{\"args\":[\"ro.config.low_ram\",\"false\"],\"result\":\"false\",\"method\":\"get\",\"type\":\"content\",\"class\":\"android.os.SystemProperties\",\"timestamp\":1507987397329},{\"args\":[\"/data/user/0/com.wsl.calorific/files/.flurryagent.743d2480\",\"577\"],\"result\":{\"descriptor\":19},\"method\":\"open\",\"type\":\"file\",\"class\":\"libcore.io.IoBridge\",\"timestamp\":1507987362574},{\"args\":[\"/data/user/0/com.wsl.calorific/files/.flurryagent.743d2480\",\"577\"],\"result\":{\"descriptor\":47},\"method\":\"open\",\"type\":\"file\",\"class\":\"libcore.io.IoBridge\",\"timestamp\":1507987432305},{\"args\":[],\"result\":\"\",\"method\":\"getNetworkCountryIso\",\"type\":\"fingerprint\",\"class\":\"android.telephony.TelephonyManager\",\"timestamp\":1507987389016},{\"args\":[\"/data/user/0/com.wsl.calorific/shared_prefs/CalorificSettings.xml\",\"577\"],\"result\":{\"descriptor\":21},\"method\":\"open\",\"type\":\"file\",\"class\":\"libcore.io.IoBridge\",\"timestamp\":1507987324529},{\"args\":[\"ro.config.low_ram\",\"false\"],\"result\":\"false\",\"method\":\"get\",\"type\":\"content\",\"class\":\"android.os.SystemProperties\",\"timestamp\":1507987397393},{\"args\":[\"debug.sqlite.journalmode\",\"PERSIST\"],\"result\":\"PERSIST\",\"method\":\"get\",\"type\":\"content\",\"class\":\"android.os.SystemProperties\",\"timestamp\":1507987324197},{\"args\":[\"key_replication_generation\",\"1\"],\"result\":{\"mClear\":false,\"mModified\":{\"key_replication_generation\":1}},\"method\":\"putInt\",\"type\":\"globals\",\"class\":\"android.app.SharedPreferencesImpl$EditorImpl\",\"timestamp\":1507987414855},{\"args\":[\"ro.config.low_ram\",\"false\"],\"result\":\"false\",\"method\":\"get\",\"type\":\"content\",\"class\":\"android.os.SystemProperties\",\"timestamp\":1507987380314},{\"args\":[\"ro.config.low_ram\",\"false\"],\"result\":\"false\",\"method\":\"get\",\"type\":\"content\",\"class\":\"android.os.SystemProperties\",\"timestamp\":1507987354545},{\"args\":[\"ro.config.low_ram\",\"false\"],\"result\":\"false\",\"method\":\"get\",\"type\":\"content\",\"class\":\"android.os.SystemProperties\",\"timestamp\":1507987414780},{\"args\":[\"/data/user/0/com.wsl.calorific/shared_prefs/CalorificSettings.xml\",\"577\"],\"result\":{\"descriptor\":60},\"method\":\"open\",\"type\":\"file\",\"class\":\"libcore.io.IoBridge\",\"timestamp\":1507987414858},{\"args\":[\"key_show_first_time_intro_screen\",\"false\"],\"result\":{\"mClear\":false,\"mModified\":{\"key_show_first_time_intro_screen\":false}},\"method\":\"putBoolean\",\"type\":\"globals\",\"class\":\"android.app.SharedPreferencesImpl$EditorImpl\",\"timestamp\":1507987324263},{\"args\":[\"ro.config.low_ram\",\"false\"],\"result\":\"false\",\"method\":\"get\",\"type\":\"content\",\"class\":\"android.os.SystemProperties\",\"timestamp\":1507987324169},{\"args\":[\"ro.config.low_ram\",\"false\"],\"result\":\"false\",\"method\":\"get\",\"type\":\"content\",\"class\":\"android.os.SystemProperties\",\"timestamp\":1507987406133},{\"args\":[\"key_first_application_start_version\",\"2.2.4\"],\"result\":{\"mClear\":false,\"mModified\":{\"key_first_application_start_version\":\"2.2.4\"}},\"method\":\"putString\",\"type\":\"globals\",\"class\":\"android.app.SharedPreferencesImpl$EditorImpl\",\"timestamp\":1507987324538},{\"args\":[\"debug.second-display.pkg\"],\"result\":\"\",\"method\":\"get\",\"type\":\"content\",\"class\":\"android.os.SystemProperties\",\"timestamp\":1507987380256},{\"args\":[{\"mDebugUnregister\":false},{\"mHasPartialTypes\":false,\"mPriority\":0,\"mActions\":[\"android.intent.action.PROXY_CHANGE\"],\"mVerifyState\":0}],\"method\":\"registerReceiver\",\"type\":\"binder\",\"class\":\"android.app.ContextImpl\",\"timestamp\":1507987388954},{\"args\":[\"ro.config.low_ram\",\"false\"],\"result\":\"false\",\"method\":\"get\",\"type\":\"content\",\"class\":\"android.os.SystemProperties\",\"timestamp\":1507987397335},{\"args\":[\"/data/data/com.devadvance.rootcloak2/shared_prefs/CustomizeKeywords.xml\",\"0\"],\"result\":{\"descriptor\":21},\"method\":\"open\",\"type\":\"file\",\"class\":\"libcore.io.IoBridge\",\"timestamp\":1507987388677},{\"args\":[\"persist.sys.timezone\"],\"result\":\"America/New_York\",\"method\":\"get\",\"type\":\"content\",\"class\":\"android.os.SystemProperties\",\"timestamp\":1507987324192},{\"args\":[\"/data/data/com.devadvance.rootcloak2/shared_prefs/CustomizeApps.xml\",\"0\"],\"result\":{\"descriptor\":19},\"method\":\"open\",\"type\":\"file\",\"class\":\"libcore.io.IoBridge\",\"timestamp\":1507987388676},{\"args\":[\"debug.sqlite.syncmode\",\"FULL\"],\"result\":\"FULL\",\"method\":\"get\",\"type\":\"content\",\"class\":\"android.os.SystemProperties\",\"timestamp\":1507987380361},{\"args\":[{\"path\":{\"decoded\":\"NOT CACHED\",\"encoded\":\"/secure/accessibility_captioning_preset\"},\"fragment\":{},\"scheme\":\"content\",\"port\":-2,\"authority\":{\"decoded\":\"settings\",\"encoded\":\"NOT CACHED\"},\"query\":{},\"uriString\":\"NOT CACHED\",\"host\":\"NOT CACHED\"},\"false\",\"android.view.accessibility.CaptioningManager$MyContentObserver@e83e2c5\",\"0\"],\"method\":\"registerContentObserver\",\"type\":\"content\",\"class\":\"android.content.ContentResolver\",\"timestamp\":1507987389369},{\"args\":[\"/data/user/0/com.wsl.calorific/shared_prefs/CalorificSettings.xml\",\"577\"],\"result\":{\"descriptor\":47},\"method\":\"open\",\"type\":\"file\",\"class\":\"libcore.io.IoBridge\",\"timestamp\":1507987414761},{\"args\":[\"/data/user/0/com.wsl.calorific/shared_prefs/CalorificSettings.xml\",\"0\"],\"result\":{\"descriptor\":15},\"method\":\"open\",\"type\":\"file\",\"class\":\"libcore.io.IoBridge\",\"timestamp\":1507987354415},{\"args\":[{\"path\":{\"decoded\":\"NOT CACHED\",\"encoded\":\"/secure/accessibility_captioning_enabled\"},\"fragment\":{},\"scheme\":\"content\",\"port\":-2,\"authority\":{\"decoded\":\"settings\",\"encoded\":\"settings\"},\"query\":{},\"uriString\":\"NOT CACHED\",\"host\":\"NOT CACHED\"},\"false\",\"android.view.accessibility.CaptioningManager$MyContentObserver@e83e2c5\"],\"method\":\"registerContentObserver\",\"type\":\"content\",\"class\":\"android.content.ContentResolver\",\"timestamp\":1507987389087},{\"args\":[\"ro.config.low_ram\",\"false\"],\"result\":\"false\",\"method\":\"get\",\"type\":\"content\",\"class\":\"android.os.SystemProperties\",\"timestamp\":1507987336576},{\"args\":[\"ro.config.low_ram\",\"false\"],\"result\":\"false\",\"method\":\"get\",\"type\":\"content\",\"class\":\"android.os.SystemProperties\",\"timestamp\":1507987432339},{\"args\":[\"ro.config.low_ram\",\"false\"],\"result\":\"false\",\"method\":\"get\",\"type\":\"content\",\"class\":\"android.os.SystemProperties\",\"timestamp\":1507987414724},{\"args\":[\"/data/user/0/com.wsl.calorific/app_webview/webview_data.lock\",\"66\"],\"result\":{\"descriptor\":23},\"method\":\"open\",\"type\":\"file\",\"class\":\"libcore.io.IoBridge\",\"timestamp\":1507987388783},{\"args\":[\"ro.config.low_ram\",\"false\"],\"result\":\"false\",\"method\":\"get\",\"type\":\"content\",\"class\":\"android.os.SystemProperties\",\"timestamp\":1507987380264},{\"args\":[\"ro.config.low_ram\",\"false\"],\"result\":\"false\",\"method\":\"get\",\"type\":\"content\",\"class\":\"android.os.SystemProperties\",\"timestamp\":1507987406049},{\"args\":[{\"act\":\"android.intent.action.MAIN\",\"cmp\":\"com.wsl.calorific/com.wsl.calorific.dashboard.DashboardActivity\"}],\"method\":\"startActivity\",\"type\":\"binder\",\"class\":\"android.app.Activity\",\"timestamp\":1507987432321},{\"args\":[\"debug.second-display.pkg\"],\"result\":\"\",\"method\":\"get\",\"type\":\"content\",\"class\":\"android.os.SystemProperties\",\"timestamp\":1507987353980},{\"args\":[\"ro.config.low_ram\",\"false\"],\"result\":\"false\",\"method\":\"get\",\"type\":\"content\",\"class\":\"android.os.SystemProperties\",\"timestamp\":1507987380263},{\"args\":[{\"path\":{\"decoded\":\"NOT CACHED\",\"encoded\":\"/secure/accessibility_captioning_foreground_color\"},\"fragment\":{},\"scheme\":\"content\",\"port\":-2,\"authority\":{\"decoded\":\"settings\",\"encoded\":\"NOT CACHED\"},\"query\":{},\"uriString\":\"NOT CACHED\",\"host\":\"NOT CACHED\"},\"false\",\"android.view.accessibility.CaptioningManager$MyContentObserver@e83e2c5\",\"0\"],\"method\":\"registerContentObserver\",\"type\":\"content\",\"class\":\"android.content.ContentResolver\",\"timestamp\":1507987389103},{\"args\":[\"/data/user/0/com.wsl.calorific/files/.flurryagent.743d2480\",\"0\"],\"result\":{\"descriptor\":19},\"method\":\"open\",\"type\":\"file\",\"class\":\"libcore.io.IoBridge\",\"timestamp\":1507987354524},{\"args\":[{\"path\":\"/data/app/com.google.android.webview-1/base.apk\"}],\"method\":\"dalvik.system.DexFile\",\"type\":\"dex\",\"class\":\"dalvik.system.DexFile\",\"timestamp\":1507987388670},{\"args\":[\"/data/user/0/com.wsl.calorific/shared_prefs/CalorificSettings.xml\",\"577\"],\"result\":{\"descriptor\":15},\"method\":\"open\",\"type\":\"file\",\"class\":\"libcore.io.IoBridge\",\"timestamp\":1507987324102},{\"args\":[\"debug.second-display.pkg\"],\"result\":\"\",\"method\":\"get\",\"type\":\"content\",\"class\":\"android.os.SystemProperties\",\"timestamp\":1507987432311},{\"args\":[\"/data/user/0/com.wsl.calorific/shared_prefs/WebViewChromiumPrefs.xml\",\"577\"],\"result\":{\"descriptor\":23},\"method\":\"open\",\"type\":\"file\",\"class\":\"libcore.io.IoBridge\",\"timestamp\":1507987388758},{\"args\":[\"gsm.operator.iso-country\"],\"result\":\"\",\"method\":\"get\",\"type\":\"content\",\"class\":\"android.os.SystemProperties\",\"timestamp\":1507987389015},{\"args\":[\"ro.config.low_ram\",\"false\"],\"result\":\"false\",\"method\":\"get\",\"type\":\"content\",\"class\":\"android.os.SystemProperties\",\"timestamp\":1507987432340},{\"args\":[\"debug.sqlite.journalmode\",\"PERSIST\"],\"result\":\"PERSIST\",\"method\":\"get\",\"type\":\"content\",\"class\":\"android.os.SystemProperties\",\"timestamp\":1507987380359},{\"args\":[\"ro.config.low_ram\",\"false\"],\"result\":\"false\",\"method\":\"get\",\"type\":\"content\",\"class\":\"android.os.SystemProperties\",\"timestamp\":1507987389043},{\"args\":[\"ro.config.low_ram\",\"false\"],\"result\":\"false\",\"method\":\"get\",\"type\":\"content\",\"class\":\"android.os.SystemProperties\",\"timestamp\":1507987414722},{\"args\":[{\"path\":{\"decoded\":\"NOT CACHED\",\"encoded\":\"/secure/accessibility_captioning_font_scale\"},\"fragment\":{},\"scheme\":\"content\",\"port\":-2,\"authority\":{\"decoded\":\"settings\",\"encoded\":\"settings\"},\"query\":{},\"uriString\":\"NOT CACHED\",\"host\":\"NOT CACHED\"},\"false\",\"android.view.accessibility.CaptioningManager$MyContentObserver@e83e2c5\"],\"method\":\"registerContentObserver\",\"type\":\"content\",\"class\":\"android.content.ContentResolver\",\"timestamp\":1507987389318},{\"args\":[\"ro.config.low_ram\",\"false\"],\"result\":\"false\",\"method\":\"get\",\"type\":\"content\",\"class\":\"android.os.SystemProperties\",\"timestamp\":1507987339692},{\"args\":[\"ro.config.low_ram\",\"false\"],\"result\":\"false\",\"method\":\"get\",\"type\":\"content\",\"class\":\"android.os.SystemProperties\",\"timestamp\":1507987406048},{\"args\":[\"/data/app/com.google.android.webview-1/base.apk\"],\"method\":\"dalvik.system.DexFile\",\"type\":\"dex\",\"class\":\"dalvik.system.DexFile\",\"timestamp\":1507987388669},{\"args\":[\"/data/user/0/com.wsl.calorific/files/.flurryagent.743d2480\",\"577\"],\"result\":{\"descriptor\":47},\"method\":\"open\",\"type\":\"file\",\"class\":\"libcore.io.IoBridge\",\"timestamp\":1507987423392},{\"args\":[\"ro.config.low_ram\",\"false\"],\"result\":\"false\",\"method\":\"get\",\"type\":\"content\",\"class\":\"android.os.SystemProperties\",\"timestamp\":1507987432337},{\"args\":[{\"path\":{\"decoded\":\"NOT CACHED\",\"encoded\":\"/secure/accessibility_captioning_preset\"},\"fragment\":{},\"scheme\":\"content\",\"port\":-2,\"authority\":{\"decoded\":\"settings\",\"encoded\":\"settings\"},\"query\":{},\"uriString\":\"NOT CACHED\",\"host\":\"NOT CACHED\"},\"false\",\"android.view.accessibility.CaptioningManager$MyContentObserver@e83e2c5\"],\"method\":\"registerContentObserver\",\"type\":\"content\",\"class\":\"android.content.ContentResolver\",\"timestamp\":1507987389385},{\"args\":[\"ro.config.low_ram\",\"false\"],\"result\":\"false\",\"method\":\"get\",\"type\":\"content\",\"class\":\"android.os.SystemProperties\",\"timestamp\":1507987324282},{\"args\":[\"webviewchromium_plat_support\"],\"result\":\"/system/lib/libwebviewchromium_plat_support.so\",\"method\":\"findLibrary\",\"type\":\"dex\",\"class\":\"dalvik.system.BaseDexClassLoader\",\"timestamp\":1507987388743},{\"args\":[\"ro.config.low_ram\",\"false\"],\"result\":\"false\",\"method\":\"get\",\"type\":\"content\",\"class\":\"android.os.SystemProperties\",\"timestamp\":1507987414721},{\"args\":[\"/data/user/0/com.wsl.calorific/files/.flurryagent.743d2480\",\"577\"],\"result\":{\"descriptor\":21},\"method\":\"open\",\"type\":\"file\",\"class\":\"libcore.io.IoBridge\",\"timestamp\":1507987353958},{\"args\":[\"ro.config.low_ram\",\"false\"],\"result\":\"false\",\"method\":\"get\",\"type\":\"content\",\"class\":\"android.os.SystemProperties\",\"timestamp\":1507987389411},{\"args\":[{\"path\":{\"decoded\":\"NOT CACHED\",\"encoded\":\"/secure/accessibility_captioning_window_color\"},\"fragment\":{},\"scheme\":\"content\",\"port\":-2,\"authority\":{\"decoded\":\"settings\",\"encoded\":\"NOT CACHED\"},\"query\":{},\"uriString\":\"NOT CACHED\",\"host\":\"NOT CACHED\"},\"false\",\"android.view.accessibility.CaptioningManager$MyContentObserver@e83e2c5\",\"0\"],\"method\":\"registerContentObserver\",\"type\":\"content\",\"class\":\"android.content.ContentResolver\",\"timestamp\":1507987389168},{\"args\":[\"/data/user/0/com.wsl.calorific/shared_prefs/CalorificSettings.xml\",\"577\"],\"result\":{\"descriptor\":16},\"method\":\"open\",\"type\":\"file\",\"class\":\"libcore.io.IoBridge\",\"timestamp\":1507987324266},{\"args\":[\"ro.config.low_ram\",\"false\"],\"result\":\"false\",\"method\":\"get\",\"type\":\"content\",\"class\":\"android.os.SystemProperties\",\"timestamp\":1507987362665},{\"args\":[\"debug.sqlite.syncmode\",\"FULL\"],\"result\":\"FULL\",\"method\":\"get\",\"type\":\"content\",\"class\":\"android.os.SystemProperties\",\"timestamp\":1507987354515},{\"args\":[{\"path\":{\"decoded\":\"NOT CACHED\",\"encoded\":\"/secure/accessibility_captioning_background_color\"},\"fragment\":{},\"scheme\":\"content\",\"port\":-2,\"authority\":{\"decoded\":\"settings\",\"encoded\":\"settings\"},\"query\":{},\"uriString\":\"NOT CACHED\",\"host\":\"NOT CACHED\"},\"false\",\"android.view.accessibility.CaptioningManager$MyContentObserver@e83e2c5\"],\"method\":\"registerContentObserver\",\"type\":\"content\",\"class\":\"android.content.ContentResolver\",\"timestamp\":1507987389152},{\"args\":[\"debug.second-display.pkg\"],\"result\":\"\",\"method\":\"get\",\"type\":\"content\",\"class\":\"android.os.SystemProperties\",\"timestamp\":1507987388602},{\"args\":[\"ro.config.low_ram\",\"false\"],\"result\":\"false\",\"method\":\"get\",\"type\":\"content\",\"class\":\"android.os.SystemProperties\",\"timestamp\":1507987397330},{\"args\":[\"debug.second-display.pkg\"],\"result\":\"\",\"method\":\"get\",\"type\":\"content\",\"class\":\"android.os.SystemProperties\",\"timestamp\":1507987397324},{\"args\":[{\"path\":{\"decoded\":\"NOT CACHED\",\"encoded\":\"/secure/accessibility_captioning_typeface\"},\"fragment\":{},\"scheme\":\"content\",\"port\":-2,\"authority\":{\"decoded\":\"settings\",\"encoded\":\"settings\"},\"query\":{},\"uriString\":\"NOT CACHED\",\"host\":\"NOT CACHED\"},\"false\",\"android.view.accessibility.CaptioningManager$MyContentObserver@e83e2c5\"],\"method\":\"registerContentObserver\",\"type\":\"content\",\"class\":\"android.content.ContentResolver\",\"timestamp\":1507987389285},{\"args\":[\"ro.config.low_ram\",\"false\"],\"result\":\"false\",\"method\":\"get\",\"type\":\"content\",\"class\":\"android.os.SystemProperties\",\"timestamp\":1507987423410},{\"args\":[\"/proc/meminfo\",\"0\"],\"result\":{\"descriptor\":27},\"method\":\"open\",\"type\":\"file\",\"class\":\"libcore.io.IoBridge\",\"timestamp\":1507987388878},{\"args\":[\"ro.config.low_ram\",\"false\"],\"result\":\"false\",\"method\":\"get\",\"type\":\"content\",\"class\":\"android.os.SystemProperties\",\"timestamp\":1507987406047},{\"args\":[\"debug.second-display.pkg\"],\"result\":\"\",\"method\":\"get\",\"type\":\"content\",\"class\":\"android.os.SystemProperties\",\"timestamp\":1507987362595},{\"args\":[\"ro.config.low_ram\",\"false\"],\"result\":\"false\",\"method\":\"get\",\"type\":\"content\",\"class\":\"android.os.SystemProperties\",\"timestamp\":1507987380265},{\"args\":[\"/data/user/0/com.wsl.calorific/files/.flurryagent.743d2480\",\"577\"],\"result\":{\"descriptor\":47},\"method\":\"open\",\"type\":\"file\",\"class\":\"libcore.io.IoBridge\",\"timestamp\":1507987414705},{\"args\":[\"web_access_code\",\"4UI5DBT8\"],\"result\":{\"mClear\":false,\"mModified\":{\"web_access_code\":\"4UI5DBT8\"}},\"method\":\"putString\",\"type\":\"globals\",\"class\":\"android.app.SharedPreferencesImpl$EditorImpl\",\"timestamp\":1507987414841},{\"args\":[\"/data/app/com.google.android.webview-1/base.apk\",\"/data/app/com.google.android.webview-1/lib/arm:/data/app/com.google.android.webview-1/base.apk!/lib/armeabi-v7a\",\"dalvik.system.PathClassLoader[DexPathList[[dex file \\\"/data/dalvik-cache/xposed_XResourcesSuperClass.dex\\\"],nativeLibraryDirectories=[/vendor/lib, /system/lib]]]\"],\"method\":\"dalvik.system.PathClassLoader\",\"type\":\"dex\",\"class\":\"dalvik.system.PathClassLoader\",\"timestamp\":1507987388671},{\"args\":[\"ro.config.low_ram\",\"false\"],\"result\":\"false\",\"method\":\"get\",\"type\":\"content\",\"class\":\"android.os.SystemProperties\",\"timestamp\":1507987414720},{\"args\":[\"debug.second-display.pkg\"],\"result\":\"\",\"method\":\"get\",\"type\":\"content\",\"class\":\"android.os.SystemProperties\",\"timestamp\":1507987406044}"}