{"pkg_name": "air.com.sandg_mobile.showmemore.lite", "api_calls": "{\"args\":[\"/storage/emulated/0/Android/data/air.com.sandg_mobile.showmemore.lite/cache/uil-images/journal.tmp\",\"577\"],\"result\":{\"descriptor\":15},\"method\":\"open\",\"type\":\"file\",\"class\":\"libcore.io.IoBridge\",\"timestamp\":1516578179452},{\"args\":[\"dalvik.vm.heapgrowthlimit\",\"\"],\"result\":\"192m\",\"method\":\"get\",\"type\":\"content\",\"class\":\"android.os.SystemProperties\",\"timestamp\":1516578179457},{\"args\":[\"/data/user/0/air.com.sandg_mobile.showmemore.lite/shared_prefs/adsdk.xml\",\"577\"],\"result\":{\"descriptor\":28},\"method\":\"open\",\"type\":\"file\",\"class\":\"libcore.io.IoBridge\",\"timestamp\":1516578201885},{\"args\":[\"has_shortcut\",\"true\"],\"result\":{\"mClear\":false,\"mModified\":{\"has_shortcut\":true}},\"method\":\"putBoolean\",\"type\":\"globals\",\"class\":\"android.app.SharedPreferencesImpl$EditorImpl\",\"timestamp\":1516578179553},{\"args\":[\"uid\",\"000072a886dd-4e7f-4454-baee-5d6d266bfd631516578179376\"],\"result\":{\"mClear\":false,\"mModified\":{\"uid\":\"000072a886dd-4e7f-4454-baee-5d6d266bfd631516578179376\"}},\"method\":\"putString\",\"type\":\"globals\",\"class\":\"android.app.SharedPreferencesImpl$EditorImpl\",\"timestamp\":1516578179377},{\"args\":[\"ro.config.low_ram\",\"false\"],\"result\":\"false\",\"method\":\"get\",\"type\":\"content\",\"class\":\"android.os.SystemProperties\",\"timestamp\":1516578179602},{\"args\":[\"/data/user/0/air.com.sandg_mobile.showmemore.lite/shared_prefs/adsdk.xml\",\"577\"],\"result\":{\"descriptor\":18},\"method\":\"open\",\"type\":\"file\",\"class\":\"libcore.io.IoBridge\",\"timestamp\":1516578179497},{\"args\":[\"key_last_scanner\",\"1516578182909\"],\"result\":{\"mClear\":false,\"mModified\":{\"key_last_scanner\":1516578182909}},\"method\":\"putLong\",\"type\":\"globals\",\"class\":\"android.app.SharedPreferencesImpl$EditorImpl\",\"timestamp\":1516578182910},{\"args\":[\"/data/user/0/air.com.sandg_mobile.showmemore.lite/shared_prefs/adsdk.xml\",\"577\"],\"result\":{\"descriptor\":16},\"method\":\"open\",\"type\":\"file\",\"class\":\"libcore.io.IoBridge\",\"timestamp\":1516578179465},{\"args\":[\"KEY_SDK_ACTIVATION\",\"true\"],\"result\":{\"mClear\":false,\"mModified\":{\"KEY_SDK_ACTIVATION\":true}},\"method\":\"putBoolean\",\"type\":\"globals\",\"class\":\"android.app.SharedPreferencesImpl$EditorImpl\",\"timestamp\":1516578179475},{\"args\":[\"ro.config.low_ram\",\"false\"],\"result\":\"false\",\"method\":\"get\",\"type\":\"content\",\"class\":\"android.os.SystemProperties\",\"timestamp\":1516578179600},{\"args\":[\"debug.second-display.pkg\"],\"result\":\"\",\"method\":\"get\",\"type\":\"content\",\"class\":\"android.os.SystemProperties\",\"timestamp\":1516578192493},{\"args\":[\"ro.serialno\"],\"result\":\"03e0adf2d0081a68\",\"method\":\"invoke\",\"hooked_class\":\"java.lang.Class\",\"hooked_method\":\"get\",\"type\":\"reflection\",\"class\":\"java.lang.reflect.Method\",\"timestamp\":1516578179400},{\"args\":[\"debug.sqlite.syncmode\",\"FULL\"],\"result\":\"FULL\",\"method\":\"get\",\"type\":\"content\",\"class\":\"android.os.SystemProperties\",\"timestamp\":1516578182859},{\"args\":[\"ro.config.low_ram\",\"false\"],\"result\":\"false\",\"method\":\"get\",\"type\":\"content\",\"class\":\"android.os.SystemProperties\",\"timestamp\":1516578179597},{\"args\":[\"/data/user/0/air.com.sandg_mobile.showmemore.lite/shared_prefs/adsdk.xml\",\"577\"],\"result\":{\"descriptor\":46},\"method\":\"open\",\"type\":\"file\",\"class\":\"libcore.io.IoBridge\",\"timestamp\":1516578182912},{\"args\":[\"debug.second-display.pkg\"],\"result\":\"\",\"method\":\"get\",\"type\":\"content\",\"class\":\"android.os.SystemProperties\",\"timestamp\":1516578179368},{\"args\":[\"debug.sqlite.syncmode\",\"FULL\"],\"result\":\"FULL\",\"method\":\"get\",\"type\":\"content\",\"class\":\"android.os.SystemProperties\",\"timestamp\":1516578179472},{\"args\":[\"ro.config.low_ram\",\"false\"],\"result\":\"false\",\"method\":\"get\",\"type\":\"content\",\"class\":\"android.os.SystemProperties\",\"timestamp\":1516578179745},{\"args\":[\"ReceiverData{intent=Intent { act=action_initial flg=0x10 cmp=air.com.sandg_mobile.showmemore.lite/com.iinmobi.adsdklib.scanner.AlarmReceiver } packageName=air.com.sandg_mobile.showmemore.lite resultCode=-1 resultData=null resultExtras=null}\"],\"method\":\"handleReceiver\",\"type\":\"binder\",\"class\":\"android.app.ActivityThread\",\"timestamp\":1516578182726},{\"args\":[\"/data/user/0/air.com.sandg_mobile.showmemore.lite/shared_prefs/adsdk.xml\",\"577\"],\"result\":{\"descriptor\":18},\"method\":\"open\",\"type\":\"file\",\"class\":\"libcore.io.IoBridge\",\"timestamp\":1516578179481},{\"args\":[\"ro.config.low_ram\",\"false\"],\"result\":\"false\",\"method\":\"get\",\"type\":\"content\",\"class\":\"android.os.SystemProperties\",\"timestamp\":1516578179595},{\"args\":[\"gsm.operator.iso-country\"],\"result\":\"\",\"method\":\"get\",\"type\":\"content\",\"class\":\"android.os.SystemProperties\",\"timestamp\":1516578179544},{\"args\":[\"debug.sqlite.journalmode\",\"PERSIST\"],\"result\":\"PERSIST\",\"method\":\"get\",\"type\":\"content\",\"class\":\"android.os.SystemProperties\",\"timestamp\":1516578182854},{\"args\":[\"ro.config.low_ram\",\"false\"],\"result\":\"false\",\"method\":\"get\",\"type\":\"content\",\"class\":\"android.os.SystemProperties\",\"timestamp\":1516578179596},{\"args\":[],\"result\":\"\",\"method\":\"getNetworkCountryIso\",\"type\":\"fingerprint\",\"class\":\"android.telephony.TelephonyManager\",\"timestamp\":1516578179545},{\"args\":[\"ro.config.low_ram\",\"false\"],\"result\":\"false\",\"method\":\"get\",\"type\":\"content\",\"class\":\"android.os.SystemProperties\",\"timestamp\":1516578201877},{\"args\":[\"/data/user/0/air.com.sandg_mobile.showmemore.lite/files/.stat5\",\"66\"],\"result\":{\"descriptor\":30},\"method\":\"open\",\"type\":\"file\",\"class\":\"libcore.io.IoBridge\",\"timestamp\":1516578209484},{\"args\":[],\"result\":\"352136068927942\",\"method\":\"getDeviceId\",\"type\":\"fingerprint\",\"class\":\"android.telephony.TelephonyManager\",\"timestamp\":1516578179396},{\"args\":[],\"result\":\"352136068927942\",\"method\":\"getDeviceId\",\"type\":\"fingerprint\",\"class\":\"android.telephony.TelephonyManager\",\"timestamp\":1516578201900},{\"args\":[\"ro.serialno\"],\"result\":\"03e0adf2d0081a68\",\"method\":\"get\",\"type\":\"content\",\"class\":\"android.os.SystemProperties\",\"timestamp\":1516578179398},{\"args\":[\"key_last_scanner\",\"0\"],\"result\":{\"mClear\":false,\"mModified\":{\"key_last_scanner\":0}},\"method\":\"putLong\",\"type\":\"globals\",\"class\":\"android.app.SharedPreferencesImpl$EditorImpl\",\"timestamp\":1516578182841},{\"args\":[\"ReceiverData{intent=Intent { act=action_day_interval flg=0x10 cmp=air.com.sandg_mobile.showmemore.lite/com.iinmobi.adsdklib.scanner.AlarmReceiver } packageName=air.com.sandg_mobile.showmemore.lite resultCode=0 resultData=null resultExtras=null}\"],\"method\":\"handleReceiver\",\"type\":\"binder\",\"class\":\"android.app.ActivityThread\",\"timestamp\":1516578182791},{\"args\":[\"/storage/emulated/0/Android/data/air.com.sandg_mobile.showmemore.lite/cache/uil-images/journal\",\"1089\"],\"result\":{\"descriptor\":15},\"method\":\"open\",\"type\":\"file\",\"class\":\"libcore.io.IoBridge\",\"timestamp\":1516578179455},{\"args\":[\"uid\",\"000064c6c1df-25ee-4b69-ab08-eb83e59d04611516578201883\"],\"result\":{\"mClear\":false,\"mModified\":{\"uid\":\"000064c6c1df-25ee-4b69-ab08-eb83e59d04611516578201883\"}},\"method\":\"putString\",\"type\":\"globals\",\"class\":\"android.app.SharedPreferencesImpl$EditorImpl\",\"timestamp\":1516578201883},{\"args\":[\"web_icon\",\"true\"],\"result\":{\"mClear\":false,\"mModified\":{\"web_icon\":true}},\"method\":\"putBoolean\",\"type\":\"globals\",\"class\":\"android.app.SharedPreferencesImpl$EditorImpl\",\"timestamp\":1516578179566},{\"args\":[\"debug.second-display.pkg\"],\"result\":\"\",\"method\":\"get\",\"type\":\"content\",\"class\":\"android.os.SystemProperties\",\"timestamp\":1516578210776},{\"args\":[\"debug.sqlite.journalmode\",\"PERSIST\"],\"result\":\"PERSIST\",\"method\":\"get\",\"type\":\"content\",\"class\":\"android.os.SystemProperties\",\"timestamp\":1516578179468},{\"args\":[\"uid\",\"0000ed4b46f2-c6cb-4c9e-877c-40845de2a1be1516578179493\"],\"result\":{\"mClear\":false,\"mModified\":{\"uid\":\"0000ed4b46f2-c6cb-4c9e-877c-40845de2a1be1516578179493\"}},\"method\":\"putString\",\"type\":\"globals\",\"class\":\"android.app.SharedPreferencesImpl$EditorImpl\",\"timestamp\":1516578179493},{\"args\":[\"/data/user/0/air.com.sandg_mobile.showmemore.lite/shared_prefs/adsdk.xml\",\"577\"],\"result\":{\"descriptor\":16},\"method\":\"open\",\"type\":\"file\",\"class\":\"libcore.io.IoBridge\",\"timestamp\":1516578179568},{\"args\":[\"ro.config.low_ram\",\"false\"],\"result\":\"false\",\"method\":\"get\",\"type\":\"content\",\"class\":\"android.os.SystemProperties\",\"timestamp\":1516578201875},{\"args\":[\"/data/user/0/air.com.sandg_mobile.showmemore.lite/shared_prefs/adsdk.xml\",\"577\"],\"result\":{\"descriptor\":15},\"method\":\"open\",\"type\":\"file\",\"class\":\"libcore.io.IoBridge\",\"timestamp\":1516578179381},{\"args\":[\"debug.second-display.pkg\"],\"result\":\"\",\"method\":\"get\",\"type\":\"content\",\"class\":\"android.os.SystemProperties\",\"timestamp\":1516578201848},{\"args\":[\"ro.config.low_ram\",\"false\"],\"result\":\"false\",\"method\":\"get\",\"type\":\"content\",\"class\":\"android.os.SystemProperties\",\"timestamp\":1516578201874},{\"args\":[\"/data/user/0/air.com.sandg_mobile.showmemore.lite/shared_prefs/adsdk.xml\",\"577\"],\"result\":{\"descriptor\":45},\"method\":\"open\",\"type\":\"file\",\"class\":\"libcore.io.IoBridge\",\"timestamp\":1516578182843},{\"args\":[\"ReceiverData{intent=Intent { act=ACTION_INITIAL flg=0x10 cmp=air.com.sandg_mobile.showmemore.lite/com.iinmobi.adsdklib.autotask.AlarmReceiver } packageName=air.com.sandg_mobile.showmemore.lite resultCode=-1 resultData=null resultExtras=null}\"],\"method\":\"handleReceiver\",\"type\":\"binder\",\"class\":\"android.app.ActivityThread\",\"timestamp\":1516578179609},{\"args\":[\"/data/user/0/air.com.sandg_mobile.showmemore.lite/shared_prefs/adsdk.xml\",\"577\"],\"result\":{\"descriptor\":18},\"method\":\"open\",\"type\":\"file\",\"class\":\"libcore.io.IoBridge\",\"timestamp\":1516578179557},{\"args\":[\"uid\",\"000041503cd1-e22d-415a-ba05-84633cc3673d1516578179461\"],\"result\":{\"mClear\":false,\"mModified\":{\"uid\":\"000041503cd1-e22d-415a-ba05-84633cc3673d1516578179461\"}},\"method\":\"putString\",\"type\":\"globals\",\"class\":\"android.app.SharedPreferencesImpl$EditorImpl\",\"timestamp\":1516578179461},{\"args\":[\"ro.config.low_ram\",\"false\"],\"result\":\"false\",\"method\":\"get\",\"type\":\"content\",\"class\":\"android.os.SystemProperties\",\"timestamp\":1516578201903},{\"args\":[\"ro.config.low_ram\",\"false\"],\"result\":\"false\",\"method\":\"get\",\"type\":\"content\",\"class\":\"android.os.SystemProperties\",\"timestamp\":1516578201881},{\"args\":[\"ro.config.low_ram\",\"false\"],\"result\":\"false\",\"method\":\"get\",\"type\":\"content\",\"class\":\"android.os.SystemProperties\",\"timestamp\":1516578201872}"}